package android.support.v4.graphics;

import android.content.Context;
import android.content.res.Resources;
import android.graphics.Typeface;
import android.support.annotation.Nullable;
import android.support.annotation.RestrictTo;
import android.support.v4.content.res.FontResourcesParserCompat.FontFamilyFilesResourceEntry;
import android.support.v4.content.res.FontResourcesParserCompat.FontFileResourceEntry;
import android.support.v4.provider.FontsContractCompat.FontInfo;

@RestrictTo({android.support.annotation.RestrictTo.Scope.LIBRARY_GROUP})
class TypefaceCompatBaseImpl
{
  private static final String CACHE_FILE_PREFIX = "cached_font_";
  private static final String TAG = "TypefaceCompatBaseImpl";
  
  private FontResourcesParserCompat.FontFileResourceEntry findBestEntry(FontResourcesParserCompat.FontFamilyFilesResourceEntry paramFontFamilyFilesResourceEntry, int paramInt)
  {
    (FontResourcesParserCompat.FontFileResourceEntry)findBestFont(paramFontFamilyFilesResourceEntry.getEntries(), paramInt, new StyleExtractor()
    {
      public int getWeight(FontResourcesParserCompat.FontFileResourceEntry paramAnonymousFontFileResourceEntry)
      {
        return paramAnonymousFontFileResourceEntry.getWeight();
      }
      
      public boolean isItalic(FontResourcesParserCompat.FontFileResourceEntry paramAnonymousFontFileResourceEntry)
      {
        return paramAnonymousFontFileResourceEntry.isItalic();
      }
    });
  }
  
  private static <T> T findBestFont(T[] paramArrayOfT, int paramInt, StyleExtractor<T> paramStyleExtractor)
  {
    int i;
    if ((paramInt & 0x1) == 0) {
      i = 400;
    } else {
      i = 700;
    }
    int i1;
    if ((paramInt & 0x2) != 0) {
      i1 = 1;
    } else {
      i1 = 0;
    }
    int n = paramArrayOfT.length;
    Object localObject = null;
    paramInt = 0;
    int k;
    for (int j = Integer.MAX_VALUE; paramInt < n; j = k)
    {
      T ? = paramArrayOfT[paramInt];
      int m = Math.abs(paramStyleExtractor.getWeight(?) - i);
      if (paramStyleExtractor.isItalic(?) == i1) {
        k = 0;
      } else {
        k = 1;
      }
      m = m * 2 + k;
      if (localObject != null)
      {
        k = j;
        if (j <= m) {}
      }
      else
      {
        localObject = ?;
        k = m;
      }
      paramInt += 1;
    }
    return (T)localObject;
  }
  
  @Nullable
  public Typeface createFromFontFamilyFilesResourceEntry(Context paramContext, FontResourcesParserCompat.FontFamilyFilesResourceEntry paramFontFamilyFilesResourceEntry, Resources paramResources, int paramInt)
  {
    paramFontFamilyFilesResourceEntry = findBestEntry(paramFontFamilyFilesResourceEntry, paramInt);
    if (paramFontFamilyFilesResourceEntry == null) {
      return null;
    }
    return TypefaceCompat.createFromResourcesFontFile(paramContext, paramResources, paramFontFamilyFilesResourceEntry.getResourceId(), paramFontFamilyFilesResourceEntry.getFileName(), paramInt);
  }
  
  /* Error */
  public Typeface createFromFontInfo(Context paramContext, @Nullable android.os.CancellationSignal paramCancellationSignal, @android.support.annotation.NonNull FontsContractCompat.FontInfo[] paramArrayOfFontInfo, int paramInt)
  {
    // Byte code:
    //   0: aload_3
    //   1: arraylength
    //   2: istore 5
    //   4: aconst_null
    //   5: astore 6
    //   7: iload 5
    //   9: ifgt +5 -> 14
    //   12: aconst_null
    //   13: areturn
    //   14: aload_0
    //   15: aload_3
    //   16: iload 4
    //   18: invokevirtual 90	android/support/v4/graphics/TypefaceCompatBaseImpl:findBestInfo	([Landroid/support/v4/provider/FontsContractCompat$FontInfo;I)Landroid/support/v4/provider/FontsContractCompat$FontInfo;
    //   21: astore_2
    //   22: aload_1
    //   23: invokevirtual 96	android/content/Context:getContentResolver	()Landroid/content/ContentResolver;
    //   26: aload_2
    //   27: invokevirtual 102	android/support/v4/provider/FontsContractCompat$FontInfo:getUri	()Landroid/net/Uri;
    //   30: invokevirtual 108	android/content/ContentResolver:openInputStream	(Landroid/net/Uri;)Ljava/io/InputStream;
    //   33: astore_2
    //   34: aload_0
    //   35: aload_1
    //   36: aload_2
    //   37: invokevirtual 112	android/support/v4/graphics/TypefaceCompatBaseImpl:createFromInputStream	(Landroid/content/Context;Ljava/io/InputStream;)Landroid/graphics/Typeface;
    //   40: astore_1
    //   41: aload_2
    //   42: invokestatic 118	android/support/v4/graphics/TypefaceCompatUtil:closeQuietly	(Ljava/io/Closeable;)V
    //   45: aload_1
    //   46: areturn
    //   47: astore_3
    //   48: aload_2
    //   49: astore_1
    //   50: aload_3
    //   51: astore_2
    //   52: goto +7 -> 59
    //   55: astore_2
    //   56: aload 6
    //   58: astore_1
    //   59: aload_1
    //   60: invokestatic 118	android/support/v4/graphics/TypefaceCompatUtil:closeQuietly	(Ljava/io/Closeable;)V
    //   63: aload_2
    //   64: athrow
    //   65: aconst_null
    //   66: astore_2
    //   67: aload_2
    //   68: invokestatic 118	android/support/v4/graphics/TypefaceCompatUtil:closeQuietly	(Ljava/io/Closeable;)V
    //   71: aconst_null
    //   72: areturn
    //   73: astore_1
    //   74: goto -9 -> 65
    //   77: astore_1
    //   78: goto -11 -> 67
    // Local variable table:
    //   start	length	slot	name	signature
    //   0	81	0	this	TypefaceCompatBaseImpl
    //   0	81	1	paramContext	Context
    //   0	81	2	paramCancellationSignal	android.os.CancellationSignal
    //   0	81	3	paramArrayOfFontInfo	FontsContractCompat.FontInfo[]
    //   0	81	4	paramInt	int
    //   2	6	5	i	int
    //   5	52	6	localObject	Object
    // Exception table:
    //   from	to	target	type
    //   34	41	47	finally
    //   22	34	55	finally
    //   22	34	73	java/io/IOException
    //   34	41	77	java/io/IOException
  }
  
  /* Error */
  protected Typeface createFromInputStream(Context paramContext, java.io.InputStream paramInputStream)
  {
    // Byte code:
    //   0: aload_1
    //   1: invokestatic 125	android/support/v4/graphics/TypefaceCompatUtil:getTempFile	(Landroid/content/Context;)Ljava/io/File;
    //   4: astore_1
    //   5: aload_1
    //   6: ifnonnull +5 -> 11
    //   9: aconst_null
    //   10: areturn
    //   11: aload_1
    //   12: aload_2
    //   13: invokestatic 129	android/support/v4/graphics/TypefaceCompatUtil:copyToFile	(Ljava/io/File;Ljava/io/InputStream;)Z
    //   16: istore_3
    //   17: iload_3
    //   18: ifne +10 -> 28
    //   21: aload_1
    //   22: invokevirtual 135	java/io/File:delete	()Z
    //   25: pop
    //   26: aconst_null
    //   27: areturn
    //   28: aload_1
    //   29: invokevirtual 138	java/io/File:getPath	()Ljava/lang/String;
    //   32: invokestatic 144	android/graphics/Typeface:createFromFile	(Ljava/lang/String;)Landroid/graphics/Typeface;
    //   35: astore_2
    //   36: aload_1
    //   37: invokevirtual 135	java/io/File:delete	()Z
    //   40: pop
    //   41: aload_2
    //   42: areturn
    //   43: astore_2
    //   44: aload_1
    //   45: invokevirtual 135	java/io/File:delete	()Z
    //   48: pop
    //   49: aload_2
    //   50: athrow
    //   51: aload_1
    //   52: invokevirtual 135	java/io/File:delete	()Z
    //   55: pop
    //   56: aconst_null
    //   57: areturn
    //   58: astore_2
    //   59: goto -8 -> 51
    // Local variable table:
    //   start	length	slot	name	signature
    //   0	62	0	this	TypefaceCompatBaseImpl
    //   0	62	1	paramContext	Context
    //   0	62	2	paramInputStream	java.io.InputStream
    //   16	2	3	bool	boolean
    // Exception table:
    //   from	to	target	type
    //   11	17	43	finally
    //   28	36	43	finally
    //   11	17	58	java/lang/RuntimeException
    //   28	36	58	java/lang/RuntimeException
  }
  
  /* Error */
  @Nullable
  public Typeface createFromResourcesFontFile(Context paramContext, Resources paramResources, int paramInt1, String paramString, int paramInt2)
  {
    // Byte code:
    //   0: aload_1
    //   1: invokestatic 125	android/support/v4/graphics/TypefaceCompatUtil:getTempFile	(Landroid/content/Context;)Ljava/io/File;
    //   4: astore_1
    //   5: aload_1
    //   6: ifnonnull +5 -> 11
    //   9: aconst_null
    //   10: areturn
    //   11: aload_1
    //   12: aload_2
    //   13: iload_3
    //   14: invokestatic 147	android/support/v4/graphics/TypefaceCompatUtil:copyToFile	(Ljava/io/File;Landroid/content/res/Resources;I)Z
    //   17: istore 6
    //   19: iload 6
    //   21: ifne +10 -> 31
    //   24: aload_1
    //   25: invokevirtual 135	java/io/File:delete	()Z
    //   28: pop
    //   29: aconst_null
    //   30: areturn
    //   31: aload_1
    //   32: invokevirtual 138	java/io/File:getPath	()Ljava/lang/String;
    //   35: invokestatic 144	android/graphics/Typeface:createFromFile	(Ljava/lang/String;)Landroid/graphics/Typeface;
    //   38: astore_2
    //   39: aload_1
    //   40: invokevirtual 135	java/io/File:delete	()Z
    //   43: pop
    //   44: aload_2
    //   45: areturn
    //   46: astore_2
    //   47: aload_1
    //   48: invokevirtual 135	java/io/File:delete	()Z
    //   51: pop
    //   52: aload_2
    //   53: athrow
    //   54: aload_1
    //   55: invokevirtual 135	java/io/File:delete	()Z
    //   58: pop
    //   59: aconst_null
    //   60: areturn
    //   61: astore_2
    //   62: goto -8 -> 54
    // Local variable table:
    //   start	length	slot	name	signature
    //   0	65	0	this	TypefaceCompatBaseImpl
    //   0	65	1	paramContext	Context
    //   0	65	2	paramResources	Resources
    //   0	65	3	paramInt1	int
    //   0	65	4	paramString	String
    //   0	65	5	paramInt2	int
    //   17	3	6	bool	boolean
    // Exception table:
    //   from	to	target	type
    //   11	19	46	finally
    //   31	39	46	finally
    //   11	19	61	java/lang/RuntimeException
    //   31	39	61	java/lang/RuntimeException
  }
  
  protected FontsContractCompat.FontInfo findBestInfo(FontsContractCompat.FontInfo[] paramArrayOfFontInfo, int paramInt)
  {
    (FontsContractCompat.FontInfo)findBestFont(paramArrayOfFontInfo, paramInt, new StyleExtractor()
    {
      public int getWeight(FontsContractCompat.FontInfo paramAnonymousFontInfo)
      {
        return paramAnonymousFontInfo.getWeight();
      }
      
      public boolean isItalic(FontsContractCompat.FontInfo paramAnonymousFontInfo)
      {
        return paramAnonymousFontInfo.isItalic();
      }
    });
  }
  
  static abstract interface StyleExtractor<T>
  {
    public abstract int getWeight(T paramT);
    
    public abstract boolean isItalic(T paramT);
  }
}


/* Location:              /home/kmille/projects/android-pwning/apks/aldi/ALDI TALK_v6.2.1_apkpure.com-dex2jar.jar!/android/support/v4/graphics/TypefaceCompatBaseImpl.class
 * Java compiler version: 6 (50.0)
 * JD-Core Version:       0.7.1
 */