package com.google.common.io;

import java.io.IOException;
import java.io.Reader;

public abstract class d
{
  public abstract Reader a()
    throws IOException;
  
  /* Error */
  public final <T> T a(i<T> parami)
    throws IOException
  {
    // Byte code:
    //   0: aload_1
    //   1: invokestatic 21	com/google/common/base/j:a	(Ljava/lang/Object;)Ljava/lang/Object;
    //   4: pop
    //   5: invokestatic 26	com/google/common/io/g:a	()Lcom/google/common/io/g;
    //   8: astore_2
    //   9: aload_2
    //   10: aload_0
    //   11: invokevirtual 28	com/google/common/io/d:a	()Ljava/io/Reader;
    //   14: invokevirtual 31	com/google/common/io/g:a	(Ljava/io/Closeable;)Ljava/io/Closeable;
    //   17: checkcast 33	java/io/Reader
    //   20: astore_3
    //   21: aload_3
    //   22: invokestatic 21	com/google/common/base/j:a	(Ljava/lang/Object;)Ljava/lang/Object;
    //   25: pop
    //   26: aload_1
    //   27: invokestatic 21	com/google/common/base/j:a	(Ljava/lang/Object;)Ljava/lang/Object;
    //   30: pop
    //   31: new 35	com/google/common/io/j
    //   34: dup
    //   35: aload_3
    //   36: invokespecial 38	com/google/common/io/j:<init>	(Ljava/lang/Readable;)V
    //   39: astore_3
    //   40: aload_3
    //   41: invokevirtual 41	com/google/common/io/j:a	()Ljava/lang/String;
    //   44: astore 4
    //   46: aload 4
    //   48: ifnull +15 -> 63
    //   51: aload_1
    //   52: aload 4
    //   54: invokeinterface 46 2 0
    //   59: pop
    //   60: goto -20 -> 40
    //   63: aload_1
    //   64: invokeinterface 49 1 0
    //   69: astore_1
    //   70: aload_2
    //   71: invokevirtual 52	com/google/common/io/g:close	()V
    //   74: aload_1
    //   75: areturn
    //   76: astore_1
    //   77: goto +10 -> 87
    //   80: astore_1
    //   81: aload_2
    //   82: aload_1
    //   83: invokevirtual 55	com/google/common/io/g:a	(Ljava/lang/Throwable;)Ljava/lang/RuntimeException;
    //   86: athrow
    //   87: aload_2
    //   88: invokevirtual 52	com/google/common/io/g:close	()V
    //   91: aload_1
    //   92: athrow
    // Local variable table:
    //   start	length	slot	name	signature
    //   0	93	0	this	d
    //   0	93	1	parami	i<T>
    //   8	80	2	localg	g
    //   20	21	3	localObject	Object
    //   44	9	4	str	String
    // Exception table:
    //   from	to	target	type
    //   9	40	76	finally
    //   40	46	76	finally
    //   51	60	76	finally
    //   63	70	76	finally
    //   81	87	76	finally
    //   9	40	80	java/lang/Throwable
    //   40	46	80	java/lang/Throwable
    //   51	60	80	java/lang/Throwable
    //   63	70	80	java/lang/Throwable
  }
  
  /* Error */
  public String b()
    throws IOException
  {
    // Byte code:
    //   0: invokestatic 26	com/google/common/io/g:a	()Lcom/google/common/io/g;
    //   3: astore_1
    //   4: aload_1
    //   5: aload_0
    //   6: invokevirtual 28	com/google/common/io/d:a	()Ljava/io/Reader;
    //   9: invokevirtual 31	com/google/common/io/g:a	(Ljava/io/Closeable;)Ljava/io/Closeable;
    //   12: checkcast 33	java/io/Reader
    //   15: invokestatic 64	com/google/common/io/e:a	(Ljava/lang/Readable;)Ljava/lang/StringBuilder;
    //   18: invokevirtual 69	java/lang/StringBuilder:toString	()Ljava/lang/String;
    //   21: astore_2
    //   22: aload_1
    //   23: invokevirtual 52	com/google/common/io/g:close	()V
    //   26: aload_2
    //   27: areturn
    //   28: astore_2
    //   29: goto +10 -> 39
    //   32: astore_2
    //   33: aload_1
    //   34: aload_2
    //   35: invokevirtual 55	com/google/common/io/g:a	(Ljava/lang/Throwable;)Ljava/lang/RuntimeException;
    //   38: athrow
    //   39: aload_1
    //   40: invokevirtual 52	com/google/common/io/g:close	()V
    //   43: aload_2
    //   44: athrow
    // Local variable table:
    //   start	length	slot	name	signature
    //   0	45	0	this	d
    //   3	37	1	localg	g
    //   21	6	2	str	String
    //   28	1	2	localObject	Object
    //   32	12	2	localThrowable	Throwable
    // Exception table:
    //   from	to	target	type
    //   4	22	28	finally
    //   33	39	28	finally
    //   4	22	32	java/lang/Throwable
  }
  
  /* Error */
  public final com.google.common.collect.l<String> c()
    throws IOException
  {
    // Byte code:
    //   0: invokestatic 26	com/google/common/io/g:a	()Lcom/google/common/io/g;
    //   3: astore_1
    //   4: aload_1
    //   5: new 73	java/io/BufferedReader
    //   8: dup
    //   9: aload_0
    //   10: invokevirtual 28	com/google/common/io/d:a	()Ljava/io/Reader;
    //   13: invokespecial 76	java/io/BufferedReader:<init>	(Ljava/io/Reader;)V
    //   16: invokevirtual 31	com/google/common/io/g:a	(Ljava/io/Closeable;)Ljava/io/Closeable;
    //   19: checkcast 73	java/io/BufferedReader
    //   22: astore_2
    //   23: invokestatic 81	com/google/common/collect/Lists:a	()Ljava/util/ArrayList;
    //   26: astore_3
    //   27: aload_2
    //   28: invokevirtual 84	java/io/BufferedReader:readLine	()Ljava/lang/String;
    //   31: astore 4
    //   33: aload 4
    //   35: ifnull +15 -> 50
    //   38: aload_3
    //   39: aload 4
    //   41: invokeinterface 90 2 0
    //   46: pop
    //   47: goto -20 -> 27
    //   50: aload_3
    //   51: invokestatic 95	com/google/common/collect/l:a	(Ljava/util/Collection;)Lcom/google/common/collect/l;
    //   54: astore_2
    //   55: aload_1
    //   56: invokevirtual 52	com/google/common/io/g:close	()V
    //   59: aload_2
    //   60: areturn
    //   61: astore_2
    //   62: goto +10 -> 72
    //   65: astore_2
    //   66: aload_1
    //   67: aload_2
    //   68: invokevirtual 55	com/google/common/io/g:a	(Ljava/lang/Throwable;)Ljava/lang/RuntimeException;
    //   71: athrow
    //   72: aload_1
    //   73: invokevirtual 52	com/google/common/io/g:close	()V
    //   76: aload_2
    //   77: athrow
    // Local variable table:
    //   start	length	slot	name	signature
    //   0	78	0	this	d
    //   3	70	1	localg	g
    //   22	38	2	localObject1	Object
    //   61	1	2	localObject2	Object
    //   65	12	2	localThrowable	Throwable
    //   26	25	3	localArrayList	java.util.ArrayList
    //   31	9	4	str	String
    // Exception table:
    //   from	to	target	type
    //   4	27	61	finally
    //   27	33	61	finally
    //   38	47	61	finally
    //   50	55	61	finally
    //   66	72	61	finally
    //   4	27	65	java/lang/Throwable
    //   27	33	65	java/lang/Throwable
    //   38	47	65	java/lang/Throwable
    //   50	55	65	java/lang/Throwable
  }
}


/* Location:              /home/kmille/projects/android-pwning/apks/aldi/ALDI TALK_v6.2.1_apkpure.com-dex2jar.jar!/com/google/common/io/d.class
 * Java compiler version: 6 (50.0)
 * JD-Core Version:       0.7.1
 */