package b.i.b.a;

import b.i.b.a.b.i;
import b.j;
import java.lang.ref.WeakReference;
import java.util.concurrent.ConcurrentHashMap;
import java.util.concurrent.ConcurrentMap;

@j(a={1, 1, 13}, b={"\000 \n\000\n\002\030\002\n\002\030\002\n\002\030\002\n\002\030\002\n\000\n\002\020\002\n\000\n\002\030\002\n\000\032\b\020\005\032\0020\006H\000\032\020\020\007\032\0020\004*\006\022\002\b\0030\bH\000\" \020\000\032\024\022\004\022\0020\002\022\n\022\b\022\004\022\0020\0040\0030\001X\004¢\006\002\n\000¨\006\t"}, c={"moduleByClassLoader", "Ljava/util/concurrent/ConcurrentMap;", "Lkotlin/reflect/jvm/internal/WeakClassLoaderBox;", "Ljava/lang/ref/WeakReference;", "Lkotlin/reflect/jvm/internal/components/RuntimeModuleData;", "clearModuleByClassLoaderCache", "", "getOrCreateModule", "Ljava/lang/Class;", "kotlin-reflect-api"})
public final class y
{
  private static final ConcurrentMap<ah, WeakReference<i>> a = (ConcurrentMap)new ConcurrentHashMap();
  
  /* Error */
  public static final i a(Class<?> paramClass)
  {
    // Byte code:
    //   0: aload_0
    //   1: ldc 37
    //   3: invokestatic 42	b/f/b/j:b	(Ljava/lang/Object;Ljava/lang/String;)V
    //   6: aload_0
    //   7: invokestatic 47	b/i/b/a/e/b:a	(Ljava/lang/Class;)Ljava/lang/ClassLoader;
    //   10: astore 10
    //   12: new 49	b/i/b/a/ah
    //   15: dup
    //   16: aload 10
    //   18: invokespecial 52	b/i/b/a/ah:<init>	(Ljava/lang/ClassLoader;)V
    //   21: astore_0
    //   22: getstatic 33	b/i/b/a/y:a	Ljava/util/concurrent/ConcurrentMap;
    //   25: aload_0
    //   26: invokeinterface 56 2 0
    //   31: checkcast 58	java/lang/ref/WeakReference
    //   34: astore_2
    //   35: aload_2
    //   36: ifnull +34 -> 70
    //   39: aload_2
    //   40: invokevirtual 61	java/lang/ref/WeakReference:get	()Ljava/lang/Object;
    //   43: checkcast 63	b/i/b/a/b/i
    //   46: astore_3
    //   47: aload_3
    //   48: ifnull +11 -> 59
    //   51: aload_3
    //   52: ldc 65
    //   54: invokestatic 67	b/f/b/j:a	(Ljava/lang/Object;Ljava/lang/String;)V
    //   57: aload_3
    //   58: areturn
    //   59: getstatic 33	b/i/b/a/y:a	Ljava/util/concurrent/ConcurrentMap;
    //   62: aload_0
    //   63: aload_2
    //   64: invokeinterface 71 3 0
    //   69: pop
    //   70: getstatic 74	b/i/b/a/b/i:c	Lb/i/b/a/b/i$a;
    //   73: astore_2
    //   74: aload 10
    //   76: ldc 76
    //   78: invokestatic 42	b/f/b/j:b	(Ljava/lang/Object;Ljava/lang/String;)V
    //   81: new 78	b/i/b/a/c/k/b
    //   84: dup
    //   85: invokespecial 79	b/i/b/a/c/k/b:<init>	()V
    //   88: checkcast 81	b/i/b/a/c/k/i
    //   91: astore_3
    //   92: new 83	b/i/b/a/c/a/b/e
    //   95: dup
    //   96: aload_3
    //   97: iconst_0
    //   98: invokespecial 86	b/i/b/a/c/a/b/e:<init>	(Lb/i/b/a/c/k/i;B)V
    //   101: astore_2
    //   102: new 88	java/lang/StringBuilder
    //   105: dup
    //   106: ldc 90
    //   108: invokespecial 93	java/lang/StringBuilder:<init>	(Ljava/lang/String;)V
    //   111: astore 4
    //   113: aload 4
    //   115: aload 10
    //   117: invokevirtual 97	java/lang/StringBuilder:append	(Ljava/lang/Object;)Ljava/lang/StringBuilder;
    //   120: pop
    //   121: aload 4
    //   123: bipush 62
    //   125: invokevirtual 100	java/lang/StringBuilder:append	(C)Ljava/lang/StringBuilder;
    //   128: pop
    //   129: aload 4
    //   131: invokevirtual 104	java/lang/StringBuilder:toString	()Ljava/lang/String;
    //   134: invokestatic 109	b/i/b/a/c/f/f:c	(Ljava/lang/String;)Lb/i/b/a/c/f/f;
    //   137: astore 4
    //   139: aload 4
    //   141: ldc 111
    //   143: invokestatic 67	b/f/b/j:a	(Ljava/lang/Object;Ljava/lang/String;)V
    //   146: new 113	b/i/b/a/c/b/c/v
    //   149: dup
    //   150: aload 4
    //   152: aload_3
    //   153: aload_2
    //   154: checkcast 115	b/i/b/a/c/a/g
    //   157: aconst_null
    //   158: bipush 56
    //   160: invokespecial 118	b/i/b/a/c/b/c/v:<init>	(Lb/i/b/a/c/f/f;Lb/i/b/a/c/k/i;Lb/i/b/a/c/a/g;Ljava/util/Map;I)V
    //   163: astore 4
    //   165: new 120	b/i/b/a/b/f
    //   168: dup
    //   169: aload 10
    //   171: invokespecial 121	b/i/b/a/b/f:<init>	(Ljava/lang/ClassLoader;)V
    //   174: astore 13
    //   176: new 123	b/i/b/a/c/d/b/e
    //   179: dup
    //   180: invokespecial 124	b/i/b/a/c/d/b/e:<init>	()V
    //   183: astore 6
    //   185: new 126	b/i/b/a/c/d/a/c/l
    //   188: dup
    //   189: invokespecial 127	b/i/b/a/c/d/a/c/l:<init>	()V
    //   192: astore 7
    //   194: new 129	b/i/b/a/b/j
    //   197: dup
    //   198: aload 10
    //   200: invokespecial 130	b/i/b/a/b/j:<init>	(Ljava/lang/ClassLoader;)V
    //   203: astore 5
    //   205: getstatic 135	b/i/b/a/c/d/a/a/g:a	Lb/i/b/a/c/d/a/a/g;
    //   208: astore 11
    //   210: aload 4
    //   212: checkcast 137	b/i/b/a/c/b/y
    //   215: astore 9
    //   217: new 139	b/i/b/a/c/b/aa
    //   220: dup
    //   221: aload_3
    //   222: aload 9
    //   224: invokespecial 142	b/i/b/a/c/b/aa:<init>	(Lb/i/b/a/c/k/i;Lb/i/b/a/c/b/y;)V
    //   227: astore 8
    //   229: new 144	b/i/b/a/c/d/a/a
    //   232: dup
    //   233: aload_3
    //   234: getstatic 150	b/i/b/a/c/n/e:g	Lb/i/b/a/c/n/e;
    //   237: invokespecial 153	b/i/b/a/c/d/a/a:<init>	(Lb/i/b/a/c/k/i;Lb/i/b/a/c/n/e;)V
    //   240: astore 12
    //   242: new 155	b/i/b/a/b/c
    //   245: dup
    //   246: aload 10
    //   248: invokespecial 156	b/i/b/a/b/c:<init>	(Ljava/lang/ClassLoader;)V
    //   251: checkcast 158	b/i/b/a/c/d/a/j
    //   254: astore 10
    //   256: aload 13
    //   258: checkcast 160	b/i/b/a/c/d/b/m
    //   261: astore 13
    //   263: getstatic 165	b/i/b/a/c/d/a/a/k:a	Lb/i/b/a/c/d/a/a/k;
    //   266: astore 14
    //   268: aload 14
    //   270: ldc -89
    //   272: invokestatic 67	b/f/b/j:a	(Ljava/lang/Object;Ljava/lang/String;)V
    //   275: getstatic 172	b/i/b/a/b/h:a	Lb/i/b/a/b/h;
    //   278: checkcast 174	b/i/b/a/c/j/a/m
    //   281: astore 15
    //   283: aload 11
    //   285: ldc -80
    //   287: invokestatic 67	b/f/b/j:a	(Ljava/lang/Object;Ljava/lang/String;)V
    //   290: new 178	b/i/b/a/c/d/a/c/g
    //   293: dup
    //   294: new 180	b/i/b/a/c/d/a/c/b
    //   297: dup
    //   298: aload_3
    //   299: aload 10
    //   301: aload 13
    //   303: aload 6
    //   305: aload 14
    //   307: aload 15
    //   309: aload 11
    //   311: getstatic 185	b/i/b/a/c/d/a/a/f$a:a	Lb/i/b/a/c/d/a/a/f$a;
    //   314: checkcast 187	b/i/b/a/c/d/a/a/f
    //   317: getstatic 192	b/i/b/a/c/d/a/a/j$a:a	Lb/i/b/a/c/d/a/a/j$a;
    //   320: checkcast 194	b/i/b/a/c/d/a/a/j
    //   323: getstatic 199	b/i/b/a/b/k:a	Lb/i/b/a/b/k;
    //   326: checkcast 201	b/i/b/a/c/d/a/d/b
    //   329: aload 7
    //   331: checkcast 203	b/i/b/a/c/d/a/c/j
    //   334: aload 5
    //   336: checkcast 205	b/i/b/a/c/d/b/s
    //   339: getstatic 210	b/i/b/a/c/b/ap$a:a	Lb/i/b/a/c/b/ap$a;
    //   342: checkcast 212	b/i/b/a/c/b/ap
    //   345: getstatic 217	b/i/b/a/c/c/a/b$a:a	Lb/i/b/a/c/c/a/b$a;
    //   348: checkcast 219	b/i/b/a/c/c/a/b
    //   351: aload 9
    //   353: new 221	b/i/b/a/c/a/i
    //   356: dup
    //   357: aload 9
    //   359: aload 8
    //   361: invokespecial 224	b/i/b/a/c/a/i:<init>	(Lb/i/b/a/c/b/y;Lb/i/b/a/c/b/aa;)V
    //   364: aload 12
    //   366: new 226	b/i/b/a/c/d/a/f/l
    //   369: dup
    //   370: aload 12
    //   372: getstatic 150	b/i/b/a/c/n/e:g	Lb/i/b/a/c/n/e;
    //   375: invokespecial 229	b/i/b/a/c/d/a/f/l:<init>	(Lb/i/b/a/c/d/a/a;Lb/i/b/a/c/n/e;)V
    //   378: getstatic 234	b/i/b/a/c/d/a/k$a:a	Lb/i/b/a/c/d/a/k$a;
    //   381: checkcast 236	b/i/b/a/c/d/a/k
    //   384: getstatic 241	b/i/b/a/c/d/a/c/c$b:b	Lb/i/b/a/c/d/a/c/c$b;
    //   387: checkcast 243	b/i/b/a/c/d/a/c/c
    //   390: invokespecial 246	b/i/b/a/c/d/a/c/b:<init>	(Lb/i/b/a/c/k/i;Lb/i/b/a/c/d/a/j;Lb/i/b/a/c/d/b/m;Lb/i/b/a/c/d/b/e;Lb/i/b/a/c/d/a/a/k;Lb/i/b/a/c/j/a/m;Lb/i/b/a/c/d/a/a/g;Lb/i/b/a/c/d/a/a/f;Lb/i/b/a/c/d/a/a/j;Lb/i/b/a/c/d/a/d/b;Lb/i/b/a/c/d/a/c/j;Lb/i/b/a/c/d/b/s;Lb/i/b/a/c/b/ap;Lb/i/b/a/c/c/a/b;Lb/i/b/a/c/b/y;Lb/i/b/a/c/a/i;Lb/i/b/a/c/d/a/a;Lb/i/b/a/c/d/a/f/l;Lb/i/b/a/c/d/a/k;Lb/i/b/a/c/d/a/c/c;)V
    //   393: invokespecial 249	b/i/b/a/c/d/a/c/g:<init>	(Lb/i/b/a/c/d/a/c/b;)V
    //   396: astore 12
    //   398: aload 9
    //   400: ldc -5
    //   402: invokestatic 42	b/f/b/j:b	(Ljava/lang/Object;Ljava/lang/String;)V
    //   405: aload_2
    //   406: getfield 255	b/i/b/a/c/a/b/e:n	Lb/i/b/a/c/b/y;
    //   409: ifnonnull +8 -> 417
    //   412: iconst_1
    //   413: istore_1
    //   414: goto +5 -> 419
    //   417: iconst_0
    //   418: istore_1
    //   419: getstatic 260	b/w:a	Z
    //   422: ifeq +24 -> 446
    //   425: iload_1
    //   426: ifeq +6 -> 432
    //   429: goto +17 -> 446
    //   432: new 262	java/lang/AssertionError
    //   435: dup
    //   436: ldc_w 264
    //   439: invokespecial 267	java/lang/AssertionError:<init>	(Ljava/lang/Object;)V
    //   442: checkcast 269	java/lang/Throwable
    //   445: athrow
    //   446: aload_2
    //   447: aload 9
    //   449: putfield 255	b/i/b/a/c/a/b/e:n	Lb/i/b/a/c/b/y;
    //   452: aload_2
    //   453: iconst_1
    //   454: putfield 272	b/i/b/a/c/a/b/e:o	Z
    //   457: new 274	b/i/b/a/c/i/d/a
    //   460: dup
    //   461: aload 12
    //   463: aload 11
    //   465: invokespecial 277	b/i/b/a/c/i/d/a:<init>	(Lb/i/b/a/c/d/a/c/g;Lb/i/b/a/c/d/a/a/g;)V
    //   468: astore 10
    //   470: new 279	b/i/b/a/c/d/b/f
    //   473: dup
    //   474: aload 13
    //   476: aload 6
    //   478: invokespecial 282	b/i/b/a/c/d/b/f:<init>	(Lb/i/b/a/c/d/b/m;Lb/i/b/a/c/d/b/e;)V
    //   481: astore 11
    //   483: new 284	b/i/b/a/c/d/b/c
    //   486: dup
    //   487: aload 9
    //   489: aload 8
    //   491: aload_3
    //   492: aload 13
    //   494: invokespecial 287	b/i/b/a/c/d/b/c:<init>	(Lb/i/b/a/c/b/y;Lb/i/b/a/c/b/aa;Lb/i/b/a/c/k/i;Lb/i/b/a/c/d/b/m;)V
    //   497: astore 13
    //   499: getstatic 292	b/i/b/a/c/j/a/j$a:a	Lb/i/b/a/c/j/a/j$a;
    //   502: checkcast 294	b/i/b/a/c/j/a/j
    //   505: astore 14
    //   507: getstatic 172	b/i/b/a/b/h:a	Lb/i/b/a/b/h;
    //   510: checkcast 174	b/i/b/a/c/j/a/m
    //   513: astore 15
    //   515: getstatic 217	b/i/b/a/c/c/a/b$a:a	Lb/i/b/a/c/c/a/b$a;
    //   518: checkcast 219	b/i/b/a/c/c/a/b
    //   521: astore 16
    //   523: getstatic 299	b/i/b/a/c/j/a/h:a	Lb/i/b/a/c/j/a/h$a;
    //   526: astore 17
    //   528: new 301	b/i/b/a/c/d/b/d
    //   531: dup
    //   532: aload_3
    //   533: aload 9
    //   535: aload 14
    //   537: aload 11
    //   539: aload 13
    //   541: aload 12
    //   543: aload 8
    //   545: aload 15
    //   547: aload 16
    //   549: invokestatic 306	b/i/b/a/c/j/a/h$a:a	()Lb/i/b/a/c/j/a/h;
    //   552: invokespecial 309	b/i/b/a/c/d/b/d:<init>	(Lb/i/b/a/c/k/i;Lb/i/b/a/c/b/y;Lb/i/b/a/c/j/a/j;Lb/i/b/a/c/d/b/f;Lb/i/b/a/c/d/b/c;Lb/i/b/a/c/d/a/c/g;Lb/i/b/a/c/b/aa;Lb/i/b/a/c/j/a/m;Lb/i/b/a/c/c/a/b;Lb/i/b/a/c/j/a/h;)V
    //   555: astore_3
    //   556: aload 10
    //   558: ldc_w 311
    //   561: invokestatic 42	b/f/b/j:b	(Ljava/lang/Object;Ljava/lang/String;)V
    //   564: aload 7
    //   566: aload 10
    //   568: putfield 314	b/i/b/a/c/d/a/c/l:a	Lb/i/b/a/c/i/d/a;
    //   571: aload_3
    //   572: ldc_w 316
    //   575: invokestatic 42	b/f/b/j:b	(Ljava/lang/Object;Ljava/lang/String;)V
    //   578: aload 6
    //   580: aload_3
    //   581: getfield 319	b/i/b/a/c/d/b/d:a	Lb/i/b/a/c/j/a/i;
    //   584: putfield 320	b/i/b/a/c/d/b/e:a	Lb/i/b/a/c/j/a/i;
    //   587: aload_2
    //   588: getfield 324	b/i/b/a/c/a/g:h	Lb/i/b/a/c/b/c/v;
    //   591: astore_2
    //   592: aload_2
    //   593: ldc_w 326
    //   596: invokestatic 67	b/f/b/j:a	(Ljava/lang/Object;Ljava/lang/String;)V
    //   599: aload 4
    //   601: iconst_2
    //   602: anewarray 113	b/i/b/a/c/b/c/v
    //   605: dup
    //   606: iconst_0
    //   607: aload 4
    //   609: aastore
    //   610: dup
    //   611: iconst_1
    //   612: aload_2
    //   613: aastore
    //   614: invokevirtual 329	b/i/b/a/c/b/c/v:a	([Lb/i/b/a/c/b/c/v;)V
    //   617: aload 4
    //   619: aload 10
    //   621: getfield 332	b/i/b/a/c/i/d/a:a	Lb/i/b/a/c/d/a/c/g;
    //   624: checkcast 334	b/i/b/a/c/b/ac
    //   627: invokevirtual 337	b/i/b/a/c/b/c/v:a	(Lb/i/b/a/c/b/ac;)V
    //   630: new 63	b/i/b/a/b/i
    //   633: dup
    //   634: aload_3
    //   635: getfield 319	b/i/b/a/c/d/b/d:a	Lb/i/b/a/c/j/a/i;
    //   638: aload 5
    //   640: iconst_0
    //   641: invokespecial 340	b/i/b/a/b/i:<init>	(Lb/i/b/a/c/j/a/i;Lb/i/b/a/b/j;B)V
    //   644: astore_3
    //   645: getstatic 33	b/i/b/a/y:a	Ljava/util/concurrent/ConcurrentMap;
    //   648: astore 4
    //   650: new 58	java/lang/ref/WeakReference
    //   653: dup
    //   654: aload_3
    //   655: invokespecial 341	java/lang/ref/WeakReference:<init>	(Ljava/lang/Object;)V
    //   658: astore 5
    //   660: aload_0
    //   661: astore_2
    //   662: aload 4
    //   664: aload_2
    //   665: aload 5
    //   667: invokeinterface 345 3 0
    //   672: checkcast 58	java/lang/ref/WeakReference
    //   675: astore 4
    //   677: aload 4
    //   679: ifnonnull +10 -> 689
    //   682: aload_2
    //   683: aconst_null
    //   684: putfield 348	b/i/b/a/ah:a	Ljava/lang/ClassLoader;
    //   687: aload_3
    //   688: areturn
    //   689: aload 4
    //   691: invokevirtual 61	java/lang/ref/WeakReference:get	()Ljava/lang/Object;
    //   694: checkcast 63	b/i/b/a/b/i
    //   697: astore 5
    //   699: aload 5
    //   701: ifnull +11 -> 712
    //   704: aload_2
    //   705: aconst_null
    //   706: putfield 348	b/i/b/a/ah:a	Ljava/lang/ClassLoader;
    //   709: aload 5
    //   711: areturn
    //   712: getstatic 33	b/i/b/a/y:a	Ljava/util/concurrent/ConcurrentMap;
    //   715: aload_2
    //   716: aload 4
    //   718: invokeinterface 71 3 0
    //   723: pop
    //   724: aload_2
    //   725: astore_0
    //   726: goto -81 -> 645
    //   729: astore_2
    //   730: goto +4 -> 734
    //   733: astore_2
    //   734: aload_0
    //   735: aconst_null
    //   736: putfield 348	b/i/b/a/ah:a	Ljava/lang/ClassLoader;
    //   739: aload_2
    //   740: athrow
    // Local variable table:
    //   start	length	slot	name	signature
    //   0	741	0	paramClass	Class<?>
    //   413	13	1	i	int
    //   34	691	2	localObject1	Object
    //   729	1	2	localObject2	Object
    //   733	7	2	localObject3	Object
    //   46	642	3	localObject4	Object
    //   111	606	4	localObject5	Object
    //   203	507	5	localObject6	Object
    //   183	396	6	locale	b.i.b.a.c.d.b.e
    //   192	373	7	locall	b.i.b.a.c.d.a.c.l
    //   227	317	8	localaa	b.i.b.a.c.b.aa
    //   215	319	9	localy	b.i.b.a.c.b.y
    //   10	610	10	localObject7	Object
    //   208	330	11	localObject8	Object
    //   240	302	12	localObject9	Object
    //   174	366	13	localObject10	Object
    //   266	270	14	localObject11	Object
    //   281	265	15	localm	b.i.b.a.c.j.a.m
    //   521	27	16	localb	b.i.b.a.c.c.a.b
    //   526	1	17	locala	b.i.b.a.c.j.a.h.a
    // Exception table:
    //   from	to	target	type
    //   662	677	729	finally
    //   689	699	729	finally
    //   712	724	729	finally
    //   645	660	733	finally
  }
}


/* Location:              /home/kmille/projects/android-pwning/apks/aldi/ALDI TALK_v6.2.1_apkpure.com-dex2jar.jar!/b/i/b/a/y.class
 * Java compiler version: 6 (50.0)
 * JD-Core Version:       0.7.1
 */