package b.i.b.a.c.e.b;

import b.i.b.a.c.e.a.a;
import b.i.b.a.c.e.a.aa;
import b.i.b.a.c.e.a.ae;
import b.i.b.a.c.e.a.c;
import b.i.b.a.c.e.a.e;
import b.i.b.a.c.e.a.o;
import b.i.b.a.c.e.a.s;
import b.i.b.a.c.e.a.u;
import b.i.b.a.c.g.d;
import b.i.b.a.c.g.f;
import b.i.b.a.c.g.g;
import b.i.b.a.c.g.i;
import b.i.b.a.c.g.i.a;
import b.i.b.a.c.g.i.f;
import b.i.b.a.c.g.j.a;
import b.i.b.a.c.g.j.b;
import b.i.b.a.c.g.q;
import b.i.b.a.c.g.r;
import b.i.b.a.c.g.s;
import b.i.b.a.c.g.z.a;
import java.io.IOException;
import java.io.InputStream;
import java.util.ArrayList;
import java.util.Collections;
import java.util.List;

public final class b
{
  public static final i.f<a.e, c> a = i.a(a.e.a(), c.a(), c.a(), 100, z.a.k, c.class);
  public static final i.f<a.o, c> b = i.a(a.o.a(), c.a(), c.a(), 100, z.a.k, c.class);
  public static final i.f<a.o, Integer> c = i.a(a.o.a(), Integer.valueOf(0), null, 101, z.a.e, Integer.class);
  public static final i.f<a.u, e> d = i.a(a.u.a(), e.a(), e.a(), 100, z.a.k, e.class);
  public static final i.f<a.u, Integer> e = i.a(a.u.a(), Integer.valueOf(0), null, 101, z.a.e, Integer.class);
  public static final i.f<a.aa, List<a.a>> f = i.a(a.aa.a(), a.a.a(), 100, z.a.k, a.a.class);
  public static final i.f<a.aa, Boolean> g = i.a(a.aa.a(), Boolean.FALSE, null, 101, z.a.h, Boolean.class);
  public static final i.f<a.ae, List<a.a>> h = i.a(a.ae.a(), a.a.a(), 100, z.a.k, a.a.class);
  public static final i.f<a.c, Integer> i = i.a(a.c.a(), Integer.valueOf(0), null, 101, z.a.e, Integer.class);
  public static final i.f<a.c, List<a.u>> j = i.a(a.c.a(), a.u.a(), 102, z.a.k, a.u.class);
  public static final i.f<a.c, Integer> k = i.a(a.c.a(), Integer.valueOf(0), null, 103, z.a.e, Integer.class);
  public static final i.f<a.s, Integer> l = i.a(a.s.a(), Integer.valueOf(0), null, 101, z.a.e, Integer.class);
  public static final i.f<a.s, List<a.u>> m = i.a(a.s.a(), a.u.a(), 102, z.a.k, a.u.class);
  
  public static void a(g paramg)
  {
    paramg.a(a);
    paramg.a(b);
    paramg.a(c);
    paramg.a(d);
    paramg.a(e);
    paramg.a(f);
    paramg.a(g);
    paramg.a(h);
    paramg.a(i);
    paramg.a(j);
    paramg.a(k);
    paramg.a(l);
    paramg.a(m);
  }
  
  public static final class a
    extends i
    implements b.b
  {
    public static s<a> a = new b.i.b.a.c.g.b() {};
    private static final a d;
    public int b;
    public int c;
    private final d e;
    private int f;
    private byte g = -1;
    private int h = -1;
    
    static
    {
      a locala = new a();
      d = locala;
      locala.k();
    }
    
    private a()
    {
      this.e = d.b;
    }
    
    /* Error */
    private a(b.i.b.a.c.g.e parame, g paramg)
      throws b.i.b.a.c.g.k
    {
      // Byte code:
      //   0: aload_0
      //   1: invokespecial 41	b/i/b/a/c/g/i:<init>	()V
      //   4: aload_0
      //   5: iconst_m1
      //   6: putfield 43	b/i/b/a/c/e/b/b$a:g	B
      //   9: aload_0
      //   10: iconst_m1
      //   11: putfield 45	b/i/b/a/c/e/b/b$a:h	I
      //   14: aload_0
      //   15: invokespecial 39	b/i/b/a/c/e/b/b$a:k	()V
      //   18: invokestatic 59	b/i/b/a/c/g/d:h	()Lb/i/b/a/c/g/d$b;
      //   21: astore 5
      //   23: aload 5
      //   25: iconst_1
      //   26: invokestatic 64	b/i/b/a/c/g/f:a	(Ljava/io/OutputStream;I)Lb/i/b/a/c/g/f;
      //   29: astore 6
      //   31: iconst_0
      //   32: istore_3
      //   33: iload_3
      //   34: ifne +158 -> 192
      //   37: aload_1
      //   38: invokevirtual 69	b/i/b/a/c/g/e:a	()I
      //   41: istore 4
      //   43: iload 4
      //   45: ifeq +75 -> 120
      //   48: iload 4
      //   50: bipush 8
      //   52: if_icmpeq +47 -> 99
      //   55: iload 4
      //   57: bipush 16
      //   59: if_icmpeq +19 -> 78
      //   62: aload_0
      //   63: aload_1
      //   64: aload 6
      //   66: aload_2
      //   67: iload 4
      //   69: invokevirtual 72	b/i/b/a/c/e/b/b$a:a	(Lb/i/b/a/c/g/e;Lb/i/b/a/c/g/f;Lb/i/b/a/c/g/g;I)Z
      //   72: ifne -39 -> 33
      //   75: goto +45 -> 120
      //   78: aload_0
      //   79: aload_0
      //   80: getfield 74	b/i/b/a/c/e/b/b$a:f	I
      //   83: iconst_2
      //   84: ior
      //   85: putfield 74	b/i/b/a/c/e/b/b$a:f	I
      //   88: aload_0
      //   89: aload_1
      //   90: invokevirtual 76	b/i/b/a/c/g/e:d	()I
      //   93: putfield 78	b/i/b/a/c/e/b/b$a:c	I
      //   96: goto -63 -> 33
      //   99: aload_0
      //   100: aload_0
      //   101: getfield 74	b/i/b/a/c/e/b/b$a:f	I
      //   104: iconst_1
      //   105: ior
      //   106: putfield 74	b/i/b/a/c/e/b/b$a:f	I
      //   109: aload_0
      //   110: aload_1
      //   111: invokevirtual 76	b/i/b/a/c/g/e:d	()I
      //   114: putfield 80	b/i/b/a/c/e/b/b$a:b	I
      //   117: goto -84 -> 33
      //   120: iconst_1
      //   121: istore_3
      //   122: goto -89 -> 33
      //   125: astore_1
      //   126: goto +31 -> 157
      //   129: astore_1
      //   130: new 54	b/i/b/a/c/g/k
      //   133: dup
      //   134: aload_1
      //   135: invokevirtual 84	java/io/IOException:getMessage	()Ljava/lang/String;
      //   138: invokespecial 87	b/i/b/a/c/g/k:<init>	(Ljava/lang/String;)V
      //   141: astore_1
      //   142: aload_1
      //   143: aload_0
      //   144: putfield 90	b/i/b/a/c/g/k:a	Lb/i/b/a/c/g/q;
      //   147: aload_1
      //   148: athrow
      //   149: astore_1
      //   150: aload_1
      //   151: aload_0
      //   152: putfield 90	b/i/b/a/c/g/k:a	Lb/i/b/a/c/g/q;
      //   155: aload_1
      //   156: athrow
      //   157: aload 6
      //   159: invokevirtual 92	b/i/b/a/c/g/f:a	()V
      //   162: aload_0
      //   163: aload 5
      //   165: invokevirtual 97	b/i/b/a/c/g/d$b:a	()Lb/i/b/a/c/g/d;
      //   168: putfield 51	b/i/b/a/c/e/b/b$a:e	Lb/i/b/a/c/g/d;
      //   171: goto +15 -> 186
      //   174: astore_1
      //   175: aload_0
      //   176: aload 5
      //   178: invokevirtual 97	b/i/b/a/c/g/d$b:a	()Lb/i/b/a/c/g/d;
      //   181: putfield 51	b/i/b/a/c/e/b/b$a:e	Lb/i/b/a/c/g/d;
      //   184: aload_1
      //   185: athrow
      //   186: aload_0
      //   187: invokevirtual 100	b/i/b/a/c/e/b/b$a:w	()V
      //   190: aload_1
      //   191: athrow
      //   192: aload 6
      //   194: invokevirtual 92	b/i/b/a/c/g/f:a	()V
      //   197: aload_0
      //   198: aload 5
      //   200: invokevirtual 97	b/i/b/a/c/g/d$b:a	()Lb/i/b/a/c/g/d;
      //   203: putfield 51	b/i/b/a/c/e/b/b$a:e	Lb/i/b/a/c/g/d;
      //   206: goto +15 -> 221
      //   209: astore_1
      //   210: aload_0
      //   211: aload 5
      //   213: invokevirtual 97	b/i/b/a/c/g/d$b:a	()Lb/i/b/a/c/g/d;
      //   216: putfield 51	b/i/b/a/c/e/b/b$a:e	Lb/i/b/a/c/g/d;
      //   219: aload_1
      //   220: athrow
      //   221: aload_0
      //   222: invokevirtual 100	b/i/b/a/c/e/b/b$a:w	()V
      //   225: return
      //   226: astore_2
      //   227: goto -65 -> 162
      //   230: astore_1
      //   231: goto -34 -> 197
      // Local variable table:
      //   start	length	slot	name	signature
      //   0	234	0	this	a
      //   0	234	1	parame	b.i.b.a.c.g.e
      //   0	234	2	paramg	g
      //   32	90	3	i	int
      //   41	27	4	j	int
      //   21	191	5	localb	b.i.b.a.c.g.d.b
      //   29	164	6	localf	f
      // Exception table:
      //   from	to	target	type
      //   37	43	125	finally
      //   62	75	125	finally
      //   78	96	125	finally
      //   99	117	125	finally
      //   130	149	125	finally
      //   150	157	125	finally
      //   37	43	129	java/io/IOException
      //   62	75	129	java/io/IOException
      //   78	96	129	java/io/IOException
      //   99	117	129	java/io/IOException
      //   37	43	149	b/i/b/a/c/g/k
      //   62	75	149	b/i/b/a/c/g/k
      //   78	96	149	b/i/b/a/c/g/k
      //   99	117	149	b/i/b/a/c/g/k
      //   157	162	174	finally
      //   192	197	209	finally
      //   157	162	226	java/io/IOException
      //   192	197	230	java/io/IOException
    }
    
    private a(i.a parama)
    {
      super();
      this.e = parama.a;
    }
    
    public static a a(a parama)
    {
      return a.g().a(parama);
    }
    
    public static a a()
    {
      return d;
    }
    
    private void k()
    {
      this.b = 0;
      this.c = 0;
    }
    
    public final void a(f paramf)
      throws IOException
    {
      f();
      if ((this.f & 0x1) == 1) {
        paramf.a(1, this.b);
      }
      if ((this.f & 0x2) == 2) {
        paramf.a(2, this.c);
      }
      paramf.c(this.e);
    }
    
    public final s<a> b()
    {
      return a;
    }
    
    public final boolean c()
    {
      return (this.f & 0x1) == 1;
    }
    
    public final boolean d()
    {
      return (this.f & 0x2) == 2;
    }
    
    public final boolean e()
    {
      int i = this.g;
      if (i == 1) {
        return true;
      }
      if (i == 0) {
        return false;
      }
      this.g = 1;
      return true;
    }
    
    public final int f()
    {
      int i = this.h;
      if (i != -1) {
        return i;
      }
      int j = this.f;
      i = 0;
      if ((j & 0x1) == 1) {
        i = 0 + f.c(1, this.b);
      }
      j = i;
      if ((this.f & 0x2) == 2) {
        j = i + f.c(2, this.c);
      }
      i = j + this.e.a();
      this.h = i;
      return i;
    }
    
    public final a g()
    {
      return a.g().a(this);
    }
    
    public static final class a
      extends i.a<b.a, a>
      implements b.b
    {
      private int b;
      private int c;
      private int d;
      
      private a a(int paramInt)
      {
        this.b |= 0x1;
        this.c = paramInt;
        return this;
      }
      
      private a b(int paramInt)
      {
        this.b |= 0x2;
        this.d = paramInt;
        return this;
      }
      
      /* Error */
      private a c(b.i.b.a.c.g.e parame, g paramg)
        throws IOException
      {
        // Byte code:
        //   0: aconst_null
        //   1: astore_3
        //   2: getstatic 36	b/i/b/a/c/e/b/b$a:a	Lb/i/b/a/c/g/s;
        //   5: aload_1
        //   6: aload_2
        //   7: invokeinterface 41 3 0
        //   12: checkcast 9	b/i/b/a/c/e/b/b$a
        //   15: astore_1
        //   16: aload_0
        //   17: aload_1
        //   18: invokevirtual 44	b/i/b/a/c/e/b/b$a$a:a	(Lb/i/b/a/c/e/b/b$a;)Lb/i/b/a/c/e/b/b$a$a;
        //   21: pop
        //   22: aload_0
        //   23: areturn
        //   24: astore_2
        //   25: aload_3
        //   26: astore_1
        //   27: goto +15 -> 42
        //   30: astore_2
        //   31: aload_2
        //   32: getfield 47	b/i/b/a/c/g/k:a	Lb/i/b/a/c/g/q;
        //   35: checkcast 9	b/i/b/a/c/e/b/b$a
        //   38: astore_1
        //   39: aload_2
        //   40: athrow
        //   41: astore_2
        //   42: aload_1
        //   43: ifnull +9 -> 52
        //   46: aload_0
        //   47: aload_1
        //   48: invokevirtual 44	b/i/b/a/c/e/b/b$a$a:a	(Lb/i/b/a/c/e/b/b$a;)Lb/i/b/a/c/e/b/b$a$a;
        //   51: pop
        //   52: aload_2
        //   53: athrow
        // Local variable table:
        //   start	length	slot	name	signature
        //   0	54	0	this	a
        //   0	54	1	parame	b.i.b.a.c.g.e
        //   0	54	2	paramg	g
        //   1	25	3	localObject	Object
        // Exception table:
        //   from	to	target	type
        //   2	16	24	finally
        //   31	39	24	finally
        //   2	16	30	b/i/b/a/c/g/k
        //   39	41	41	finally
      }
      
      private a h()
      {
        return new a().a(f());
      }
      
      public final a a(b.a parama)
      {
        if (parama == b.a.a()) {
          return this;
        }
        if (parama.c()) {
          a(parama.b);
        }
        if (parama.d()) {
          b(parama.c);
        }
        this.a = this.a.a(b.a.b(parama));
        return this;
      }
      
      public final boolean e()
      {
        return true;
      }
      
      public final b.a f()
      {
        int i = 0;
        b.a locala = new b.a(this, (byte)0);
        int k = this.b;
        if ((k & 0x1) == 1) {
          i = 1;
        }
        b.a.a(locala, this.c);
        int j = i;
        if ((k & 0x2) == 2) {
          j = i | 0x2;
        }
        b.a.b(locala, this.d);
        b.a.c(locala, j);
        return locala;
      }
    }
  }
  
  public static abstract interface b
    extends r
  {}
  
  public static final class c
    extends i
    implements b.d
  {
    public static s<c> a = new b.i.b.a.c.g.b() {};
    private static final c d;
    public int b;
    public int c;
    private final d e;
    private int f;
    private byte g = -1;
    private int h = -1;
    
    static
    {
      c localc = new c();
      d = localc;
      localc.k();
    }
    
    private c()
    {
      this.e = d.b;
    }
    
    /* Error */
    private c(b.i.b.a.c.g.e parame, g paramg)
      throws b.i.b.a.c.g.k
    {
      // Byte code:
      //   0: aload_0
      //   1: invokespecial 41	b/i/b/a/c/g/i:<init>	()V
      //   4: aload_0
      //   5: iconst_m1
      //   6: putfield 43	b/i/b/a/c/e/b/b$c:g	B
      //   9: aload_0
      //   10: iconst_m1
      //   11: putfield 45	b/i/b/a/c/e/b/b$c:h	I
      //   14: aload_0
      //   15: invokespecial 39	b/i/b/a/c/e/b/b$c:k	()V
      //   18: invokestatic 59	b/i/b/a/c/g/d:h	()Lb/i/b/a/c/g/d$b;
      //   21: astore 5
      //   23: aload 5
      //   25: iconst_1
      //   26: invokestatic 64	b/i/b/a/c/g/f:a	(Ljava/io/OutputStream;I)Lb/i/b/a/c/g/f;
      //   29: astore 6
      //   31: iconst_0
      //   32: istore_3
      //   33: iload_3
      //   34: ifne +158 -> 192
      //   37: aload_1
      //   38: invokevirtual 69	b/i/b/a/c/g/e:a	()I
      //   41: istore 4
      //   43: iload 4
      //   45: ifeq +75 -> 120
      //   48: iload 4
      //   50: bipush 8
      //   52: if_icmpeq +47 -> 99
      //   55: iload 4
      //   57: bipush 16
      //   59: if_icmpeq +19 -> 78
      //   62: aload_0
      //   63: aload_1
      //   64: aload 6
      //   66: aload_2
      //   67: iload 4
      //   69: invokevirtual 72	b/i/b/a/c/e/b/b$c:a	(Lb/i/b/a/c/g/e;Lb/i/b/a/c/g/f;Lb/i/b/a/c/g/g;I)Z
      //   72: ifne -39 -> 33
      //   75: goto +45 -> 120
      //   78: aload_0
      //   79: aload_0
      //   80: getfield 74	b/i/b/a/c/e/b/b$c:f	I
      //   83: iconst_2
      //   84: ior
      //   85: putfield 74	b/i/b/a/c/e/b/b$c:f	I
      //   88: aload_0
      //   89: aload_1
      //   90: invokevirtual 76	b/i/b/a/c/g/e:d	()I
      //   93: putfield 78	b/i/b/a/c/e/b/b$c:c	I
      //   96: goto -63 -> 33
      //   99: aload_0
      //   100: aload_0
      //   101: getfield 74	b/i/b/a/c/e/b/b$c:f	I
      //   104: iconst_1
      //   105: ior
      //   106: putfield 74	b/i/b/a/c/e/b/b$c:f	I
      //   109: aload_0
      //   110: aload_1
      //   111: invokevirtual 76	b/i/b/a/c/g/e:d	()I
      //   114: putfield 80	b/i/b/a/c/e/b/b$c:b	I
      //   117: goto -84 -> 33
      //   120: iconst_1
      //   121: istore_3
      //   122: goto -89 -> 33
      //   125: astore_1
      //   126: goto +31 -> 157
      //   129: astore_1
      //   130: new 54	b/i/b/a/c/g/k
      //   133: dup
      //   134: aload_1
      //   135: invokevirtual 84	java/io/IOException:getMessage	()Ljava/lang/String;
      //   138: invokespecial 87	b/i/b/a/c/g/k:<init>	(Ljava/lang/String;)V
      //   141: astore_1
      //   142: aload_1
      //   143: aload_0
      //   144: putfield 90	b/i/b/a/c/g/k:a	Lb/i/b/a/c/g/q;
      //   147: aload_1
      //   148: athrow
      //   149: astore_1
      //   150: aload_1
      //   151: aload_0
      //   152: putfield 90	b/i/b/a/c/g/k:a	Lb/i/b/a/c/g/q;
      //   155: aload_1
      //   156: athrow
      //   157: aload 6
      //   159: invokevirtual 92	b/i/b/a/c/g/f:a	()V
      //   162: aload_0
      //   163: aload 5
      //   165: invokevirtual 97	b/i/b/a/c/g/d$b:a	()Lb/i/b/a/c/g/d;
      //   168: putfield 51	b/i/b/a/c/e/b/b$c:e	Lb/i/b/a/c/g/d;
      //   171: goto +15 -> 186
      //   174: astore_1
      //   175: aload_0
      //   176: aload 5
      //   178: invokevirtual 97	b/i/b/a/c/g/d$b:a	()Lb/i/b/a/c/g/d;
      //   181: putfield 51	b/i/b/a/c/e/b/b$c:e	Lb/i/b/a/c/g/d;
      //   184: aload_1
      //   185: athrow
      //   186: aload_0
      //   187: invokevirtual 100	b/i/b/a/c/e/b/b$c:w	()V
      //   190: aload_1
      //   191: athrow
      //   192: aload 6
      //   194: invokevirtual 92	b/i/b/a/c/g/f:a	()V
      //   197: aload_0
      //   198: aload 5
      //   200: invokevirtual 97	b/i/b/a/c/g/d$b:a	()Lb/i/b/a/c/g/d;
      //   203: putfield 51	b/i/b/a/c/e/b/b$c:e	Lb/i/b/a/c/g/d;
      //   206: goto +15 -> 221
      //   209: astore_1
      //   210: aload_0
      //   211: aload 5
      //   213: invokevirtual 97	b/i/b/a/c/g/d$b:a	()Lb/i/b/a/c/g/d;
      //   216: putfield 51	b/i/b/a/c/e/b/b$c:e	Lb/i/b/a/c/g/d;
      //   219: aload_1
      //   220: athrow
      //   221: aload_0
      //   222: invokevirtual 100	b/i/b/a/c/e/b/b$c:w	()V
      //   225: return
      //   226: astore_2
      //   227: goto -65 -> 162
      //   230: astore_1
      //   231: goto -34 -> 197
      // Local variable table:
      //   start	length	slot	name	signature
      //   0	234	0	this	c
      //   0	234	1	parame	b.i.b.a.c.g.e
      //   0	234	2	paramg	g
      //   32	90	3	i	int
      //   41	27	4	j	int
      //   21	191	5	localb	b.i.b.a.c.g.d.b
      //   29	164	6	localf	f
      // Exception table:
      //   from	to	target	type
      //   37	43	125	finally
      //   62	75	125	finally
      //   78	96	125	finally
      //   99	117	125	finally
      //   130	149	125	finally
      //   150	157	125	finally
      //   37	43	129	java/io/IOException
      //   62	75	129	java/io/IOException
      //   78	96	129	java/io/IOException
      //   99	117	129	java/io/IOException
      //   37	43	149	b/i/b/a/c/g/k
      //   62	75	149	b/i/b/a/c/g/k
      //   78	96	149	b/i/b/a/c/g/k
      //   99	117	149	b/i/b/a/c/g/k
      //   157	162	174	finally
      //   192	197	209	finally
      //   157	162	226	java/io/IOException
      //   192	197	230	java/io/IOException
    }
    
    private c(i.a parama)
    {
      super();
      this.e = parama.a;
    }
    
    public static a a(c paramc)
    {
      return a.g().a(paramc);
    }
    
    public static c a()
    {
      return d;
    }
    
    private void k()
    {
      this.b = 0;
      this.c = 0;
    }
    
    public final void a(f paramf)
      throws IOException
    {
      f();
      if ((this.f & 0x1) == 1) {
        paramf.a(1, this.b);
      }
      if ((this.f & 0x2) == 2) {
        paramf.a(2, this.c);
      }
      paramf.c(this.e);
    }
    
    public final s<c> b()
    {
      return a;
    }
    
    public final boolean c()
    {
      return (this.f & 0x1) == 1;
    }
    
    public final boolean d()
    {
      return (this.f & 0x2) == 2;
    }
    
    public final boolean e()
    {
      int i = this.g;
      if (i == 1) {
        return true;
      }
      if (i == 0) {
        return false;
      }
      this.g = 1;
      return true;
    }
    
    public final int f()
    {
      int i = this.h;
      if (i != -1) {
        return i;
      }
      int j = this.f;
      i = 0;
      if ((j & 0x1) == 1) {
        i = 0 + f.c(1, this.b);
      }
      j = i;
      if ((this.f & 0x2) == 2) {
        j = i + f.c(2, this.c);
      }
      i = j + this.e.a();
      this.h = i;
      return i;
    }
    
    public final a g()
    {
      return a.g().a(this);
    }
    
    public static final class a
      extends i.a<b.c, a>
      implements b.d
    {
      private int b;
      private int c;
      private int d;
      
      private a a(int paramInt)
      {
        this.b |= 0x1;
        this.c = paramInt;
        return this;
      }
      
      private a b(int paramInt)
      {
        this.b |= 0x2;
        this.d = paramInt;
        return this;
      }
      
      /* Error */
      private a c(b.i.b.a.c.g.e parame, g paramg)
        throws IOException
      {
        // Byte code:
        //   0: aconst_null
        //   1: astore_3
        //   2: getstatic 36	b/i/b/a/c/e/b/b$c:a	Lb/i/b/a/c/g/s;
        //   5: aload_1
        //   6: aload_2
        //   7: invokeinterface 41 3 0
        //   12: checkcast 9	b/i/b/a/c/e/b/b$c
        //   15: astore_1
        //   16: aload_0
        //   17: aload_1
        //   18: invokevirtual 44	b/i/b/a/c/e/b/b$c$a:a	(Lb/i/b/a/c/e/b/b$c;)Lb/i/b/a/c/e/b/b$c$a;
        //   21: pop
        //   22: aload_0
        //   23: areturn
        //   24: astore_2
        //   25: aload_3
        //   26: astore_1
        //   27: goto +15 -> 42
        //   30: astore_2
        //   31: aload_2
        //   32: getfield 47	b/i/b/a/c/g/k:a	Lb/i/b/a/c/g/q;
        //   35: checkcast 9	b/i/b/a/c/e/b/b$c
        //   38: astore_1
        //   39: aload_2
        //   40: athrow
        //   41: astore_2
        //   42: aload_1
        //   43: ifnull +9 -> 52
        //   46: aload_0
        //   47: aload_1
        //   48: invokevirtual 44	b/i/b/a/c/e/b/b$c$a:a	(Lb/i/b/a/c/e/b/b$c;)Lb/i/b/a/c/e/b/b$c$a;
        //   51: pop
        //   52: aload_2
        //   53: athrow
        // Local variable table:
        //   start	length	slot	name	signature
        //   0	54	0	this	a
        //   0	54	1	parame	b.i.b.a.c.g.e
        //   0	54	2	paramg	g
        //   1	25	3	localObject	Object
        // Exception table:
        //   from	to	target	type
        //   2	16	24	finally
        //   31	39	24	finally
        //   2	16	30	b/i/b/a/c/g/k
        //   39	41	41	finally
      }
      
      private a h()
      {
        return new a().a(f());
      }
      
      public final a a(b.c paramc)
      {
        if (paramc == b.c.a()) {
          return this;
        }
        if (paramc.c()) {
          a(paramc.b);
        }
        if (paramc.d()) {
          b(paramc.c);
        }
        this.a = this.a.a(b.c.b(paramc));
        return this;
      }
      
      public final boolean e()
      {
        return true;
      }
      
      public final b.c f()
      {
        int i = 0;
        b.c localc = new b.c(this, (byte)0);
        int k = this.b;
        if ((k & 0x1) == 1) {
          i = 1;
        }
        b.c.a(localc, this.c);
        int j = i;
        if ((k & 0x2) == 2) {
          j = i | 0x2;
        }
        b.c.b(localc, this.d);
        b.c.c(localc, j);
        return localc;
      }
    }
  }
  
  public static abstract interface d
    extends r
  {}
  
  public static final class e
    extends i
    implements b.f
  {
    public static s<e> a = new b.i.b.a.c.g.b() {};
    private static final e f;
    public b.a b;
    public b.c c;
    public b.c d;
    public b.c e;
    private final d g;
    private int h;
    private byte i = -1;
    private int j = -1;
    
    static
    {
      e locale = new e();
      f = locale;
      locale.l();
    }
    
    private e()
    {
      this.g = d.b;
    }
    
    /* Error */
    private e(b.i.b.a.c.g.e parame, g paramg)
      throws b.i.b.a.c.g.k
    {
      // Byte code:
      //   0: aload_0
      //   1: invokespecial 45	b/i/b/a/c/g/i:<init>	()V
      //   4: aload_0
      //   5: iconst_m1
      //   6: putfield 47	b/i/b/a/c/e/b/b$e:i	B
      //   9: aload_0
      //   10: iconst_m1
      //   11: putfield 49	b/i/b/a/c/e/b/b$e:j	I
      //   14: aload_0
      //   15: invokespecial 43	b/i/b/a/c/e/b/b$e:l	()V
      //   18: invokestatic 63	b/i/b/a/c/g/d:h	()Lb/i/b/a/c/g/d$b;
      //   21: astore 10
      //   23: aload 10
      //   25: iconst_1
      //   26: invokestatic 68	b/i/b/a/c/g/f:a	(Ljava/io/OutputStream;I)Lb/i/b/a/c/g/f;
      //   29: astore 11
      //   31: iconst_0
      //   32: istore 5
      //   34: iload 5
      //   36: ifne +443 -> 479
      //   39: aload_1
      //   40: invokevirtual 73	b/i/b/a/c/g/e:a	()I
      //   43: istore_3
      //   44: iload_3
      //   45: ifeq +361 -> 406
      //   48: aconst_null
      //   49: astore 7
      //   51: aconst_null
      //   52: astore 8
      //   54: aconst_null
      //   55: astore 9
      //   57: aconst_null
      //   58: astore 6
      //   60: iload_3
      //   61: bipush 10
      //   63: if_icmpeq +268 -> 331
      //   66: iload_3
      //   67: bipush 18
      //   69: if_icmpeq +187 -> 256
      //   72: iload_3
      //   73: bipush 26
      //   75: if_icmpeq +106 -> 181
      //   78: iload_3
      //   79: bipush 34
      //   81: if_icmpeq +18 -> 99
      //   84: aload_0
      //   85: aload_1
      //   86: aload 11
      //   88: aload_2
      //   89: iload_3
      //   90: invokevirtual 76	b/i/b/a/c/e/b/b$e:a	(Lb/i/b/a/c/g/e;Lb/i/b/a/c/g/f;Lb/i/b/a/c/g/g;I)Z
      //   93: ifne -59 -> 34
      //   96: goto +310 -> 406
      //   99: aload_0
      //   100: getfield 78	b/i/b/a/c/e/b/b$e:h	I
      //   103: istore_3
      //   104: bipush 8
      //   106: istore 4
      //   108: iload_3
      //   109: bipush 8
      //   111: iand
      //   112: bipush 8
      //   114: if_icmpne +12 -> 126
      //   117: aload_0
      //   118: getfield 80	b/i/b/a/c/e/b/b$e:e	Lb/i/b/a/c/e/b/b$c;
      //   121: invokevirtual 85	b/i/b/a/c/e/b/b$c:g	()Lb/i/b/a/c/e/b/b$c$a;
      //   124: astore 6
      //   126: aload_0
      //   127: aload_1
      //   128: getstatic 86	b/i/b/a/c/e/b/b$c:a	Lb/i/b/a/c/g/s;
      //   131: aload_2
      //   132: invokevirtual 89	b/i/b/a/c/g/e:a	(Lb/i/b/a/c/g/s;Lb/i/b/a/c/g/g;)Lb/i/b/a/c/g/q;
      //   135: checkcast 82	b/i/b/a/c/e/b/b$c
      //   138: putfield 80	b/i/b/a/c/e/b/b$e:e	Lb/i/b/a/c/e/b/b$c;
      //   141: aload 6
      //   143: ifnull +22 -> 165
      //   146: aload 6
      //   148: aload_0
      //   149: getfield 80	b/i/b/a/c/e/b/b$e:e	Lb/i/b/a/c/e/b/b$c;
      //   152: invokevirtual 94	b/i/b/a/c/e/b/b$c$a:a	(Lb/i/b/a/c/e/b/b$c;)Lb/i/b/a/c/e/b/b$c$a;
      //   155: pop
      //   156: aload_0
      //   157: aload 6
      //   159: invokevirtual 97	b/i/b/a/c/e/b/b$c$a:f	()Lb/i/b/a/c/e/b/b$c;
      //   162: putfield 80	b/i/b/a/c/e/b/b$e:e	Lb/i/b/a/c/e/b/b$c;
      //   165: aload_0
      //   166: getfield 78	b/i/b/a/c/e/b/b$e:h	I
      //   169: istore_3
      //   170: aload_0
      //   171: iload_3
      //   172: iload 4
      //   174: ior
      //   175: putfield 78	b/i/b/a/c/e/b/b$e:h	I
      //   178: goto -144 -> 34
      //   181: aload_0
      //   182: getfield 78	b/i/b/a/c/e/b/b$e:h	I
      //   185: istore_3
      //   186: iconst_4
      //   187: istore 4
      //   189: aload 7
      //   191: astore 6
      //   193: iload_3
      //   194: iconst_4
      //   195: iand
      //   196: iconst_4
      //   197: if_icmpne +12 -> 209
      //   200: aload_0
      //   201: getfield 99	b/i/b/a/c/e/b/b$e:d	Lb/i/b/a/c/e/b/b$c;
      //   204: invokevirtual 85	b/i/b/a/c/e/b/b$c:g	()Lb/i/b/a/c/e/b/b$c$a;
      //   207: astore 6
      //   209: aload_0
      //   210: aload_1
      //   211: getstatic 86	b/i/b/a/c/e/b/b$c:a	Lb/i/b/a/c/g/s;
      //   214: aload_2
      //   215: invokevirtual 89	b/i/b/a/c/g/e:a	(Lb/i/b/a/c/g/s;Lb/i/b/a/c/g/g;)Lb/i/b/a/c/g/q;
      //   218: checkcast 82	b/i/b/a/c/e/b/b$c
      //   221: putfield 99	b/i/b/a/c/e/b/b$e:d	Lb/i/b/a/c/e/b/b$c;
      //   224: aload 6
      //   226: ifnull +22 -> 248
      //   229: aload 6
      //   231: aload_0
      //   232: getfield 99	b/i/b/a/c/e/b/b$e:d	Lb/i/b/a/c/e/b/b$c;
      //   235: invokevirtual 94	b/i/b/a/c/e/b/b$c$a:a	(Lb/i/b/a/c/e/b/b$c;)Lb/i/b/a/c/e/b/b$c$a;
      //   238: pop
      //   239: aload_0
      //   240: aload 6
      //   242: invokevirtual 97	b/i/b/a/c/e/b/b$c$a:f	()Lb/i/b/a/c/e/b/b$c;
      //   245: putfield 99	b/i/b/a/c/e/b/b$e:d	Lb/i/b/a/c/e/b/b$c;
      //   248: aload_0
      //   249: getfield 78	b/i/b/a/c/e/b/b$e:h	I
      //   252: istore_3
      //   253: goto -83 -> 170
      //   256: aload_0
      //   257: getfield 78	b/i/b/a/c/e/b/b$e:h	I
      //   260: istore_3
      //   261: iconst_2
      //   262: istore 4
      //   264: aload 8
      //   266: astore 6
      //   268: iload_3
      //   269: iconst_2
      //   270: iand
      //   271: iconst_2
      //   272: if_icmpne +12 -> 284
      //   275: aload_0
      //   276: getfield 101	b/i/b/a/c/e/b/b$e:c	Lb/i/b/a/c/e/b/b$c;
      //   279: invokevirtual 85	b/i/b/a/c/e/b/b$c:g	()Lb/i/b/a/c/e/b/b$c$a;
      //   282: astore 6
      //   284: aload_0
      //   285: aload_1
      //   286: getstatic 86	b/i/b/a/c/e/b/b$c:a	Lb/i/b/a/c/g/s;
      //   289: aload_2
      //   290: invokevirtual 89	b/i/b/a/c/g/e:a	(Lb/i/b/a/c/g/s;Lb/i/b/a/c/g/g;)Lb/i/b/a/c/g/q;
      //   293: checkcast 82	b/i/b/a/c/e/b/b$c
      //   296: putfield 101	b/i/b/a/c/e/b/b$e:c	Lb/i/b/a/c/e/b/b$c;
      //   299: aload 6
      //   301: ifnull +22 -> 323
      //   304: aload 6
      //   306: aload_0
      //   307: getfield 101	b/i/b/a/c/e/b/b$e:c	Lb/i/b/a/c/e/b/b$c;
      //   310: invokevirtual 94	b/i/b/a/c/e/b/b$c$a:a	(Lb/i/b/a/c/e/b/b$c;)Lb/i/b/a/c/e/b/b$c$a;
      //   313: pop
      //   314: aload_0
      //   315: aload 6
      //   317: invokevirtual 97	b/i/b/a/c/e/b/b$c$a:f	()Lb/i/b/a/c/e/b/b$c;
      //   320: putfield 101	b/i/b/a/c/e/b/b$e:c	Lb/i/b/a/c/e/b/b$c;
      //   323: aload_0
      //   324: getfield 78	b/i/b/a/c/e/b/b$e:h	I
      //   327: istore_3
      //   328: goto -158 -> 170
      //   331: aload 9
      //   333: astore 6
      //   335: aload_0
      //   336: getfield 78	b/i/b/a/c/e/b/b$e:h	I
      //   339: iconst_1
      //   340: iand
      //   341: iconst_1
      //   342: if_icmpne +12 -> 354
      //   345: aload_0
      //   346: getfield 103	b/i/b/a/c/e/b/b$e:b	Lb/i/b/a/c/e/b/b$a;
      //   349: invokevirtual 108	b/i/b/a/c/e/b/b$a:g	()Lb/i/b/a/c/e/b/b$a$a;
      //   352: astore 6
      //   354: aload_0
      //   355: aload_1
      //   356: getstatic 109	b/i/b/a/c/e/b/b$a:a	Lb/i/b/a/c/g/s;
      //   359: aload_2
      //   360: invokevirtual 89	b/i/b/a/c/g/e:a	(Lb/i/b/a/c/g/s;Lb/i/b/a/c/g/g;)Lb/i/b/a/c/g/q;
      //   363: checkcast 105	b/i/b/a/c/e/b/b$a
      //   366: putfield 103	b/i/b/a/c/e/b/b$e:b	Lb/i/b/a/c/e/b/b$a;
      //   369: aload 6
      //   371: ifnull +22 -> 393
      //   374: aload 6
      //   376: aload_0
      //   377: getfield 103	b/i/b/a/c/e/b/b$e:b	Lb/i/b/a/c/e/b/b$a;
      //   380: invokevirtual 114	b/i/b/a/c/e/b/b$a$a:a	(Lb/i/b/a/c/e/b/b$a;)Lb/i/b/a/c/e/b/b$a$a;
      //   383: pop
      //   384: aload_0
      //   385: aload 6
      //   387: invokevirtual 117	b/i/b/a/c/e/b/b$a$a:f	()Lb/i/b/a/c/e/b/b$a;
      //   390: putfield 103	b/i/b/a/c/e/b/b$e:b	Lb/i/b/a/c/e/b/b$a;
      //   393: aload_0
      //   394: aload_0
      //   395: getfield 78	b/i/b/a/c/e/b/b$e:h	I
      //   398: iconst_1
      //   399: ior
      //   400: putfield 78	b/i/b/a/c/e/b/b$e:h	I
      //   403: goto -369 -> 34
      //   406: iconst_1
      //   407: istore 5
      //   409: goto -375 -> 34
      //   412: astore_1
      //   413: goto +31 -> 444
      //   416: astore_1
      //   417: new 58	b/i/b/a/c/g/k
      //   420: dup
      //   421: aload_1
      //   422: invokevirtual 121	java/io/IOException:getMessage	()Ljava/lang/String;
      //   425: invokespecial 124	b/i/b/a/c/g/k:<init>	(Ljava/lang/String;)V
      //   428: astore_1
      //   429: aload_1
      //   430: aload_0
      //   431: putfield 127	b/i/b/a/c/g/k:a	Lb/i/b/a/c/g/q;
      //   434: aload_1
      //   435: athrow
      //   436: astore_1
      //   437: aload_1
      //   438: aload_0
      //   439: putfield 127	b/i/b/a/c/g/k:a	Lb/i/b/a/c/g/q;
      //   442: aload_1
      //   443: athrow
      //   444: aload 11
      //   446: invokevirtual 129	b/i/b/a/c/g/f:a	()V
      //   449: aload_0
      //   450: aload 10
      //   452: invokevirtual 134	b/i/b/a/c/g/d$b:a	()Lb/i/b/a/c/g/d;
      //   455: putfield 55	b/i/b/a/c/e/b/b$e:g	Lb/i/b/a/c/g/d;
      //   458: goto +15 -> 473
      //   461: astore_1
      //   462: aload_0
      //   463: aload 10
      //   465: invokevirtual 134	b/i/b/a/c/g/d$b:a	()Lb/i/b/a/c/g/d;
      //   468: putfield 55	b/i/b/a/c/e/b/b$e:g	Lb/i/b/a/c/g/d;
      //   471: aload_1
      //   472: athrow
      //   473: aload_0
      //   474: invokevirtual 137	b/i/b/a/c/e/b/b$e:w	()V
      //   477: aload_1
      //   478: athrow
      //   479: aload 11
      //   481: invokevirtual 129	b/i/b/a/c/g/f:a	()V
      //   484: aload_0
      //   485: aload 10
      //   487: invokevirtual 134	b/i/b/a/c/g/d$b:a	()Lb/i/b/a/c/g/d;
      //   490: putfield 55	b/i/b/a/c/e/b/b$e:g	Lb/i/b/a/c/g/d;
      //   493: goto +15 -> 508
      //   496: astore_1
      //   497: aload_0
      //   498: aload 10
      //   500: invokevirtual 134	b/i/b/a/c/g/d$b:a	()Lb/i/b/a/c/g/d;
      //   503: putfield 55	b/i/b/a/c/e/b/b$e:g	Lb/i/b/a/c/g/d;
      //   506: aload_1
      //   507: athrow
      //   508: aload_0
      //   509: invokevirtual 137	b/i/b/a/c/e/b/b$e:w	()V
      //   512: return
      //   513: astore_2
      //   514: goto -65 -> 449
      //   517: astore_1
      //   518: goto -34 -> 484
      // Local variable table:
      //   start	length	slot	name	signature
      //   0	521	0	this	e
      //   0	521	1	parame	b.i.b.a.c.g.e
      //   0	521	2	paramg	g
      //   43	285	3	k	int
      //   106	157	4	m	int
      //   32	376	5	n	int
      //   58	328	6	localObject1	Object
      //   49	141	7	localObject2	Object
      //   52	213	8	localObject3	Object
      //   55	277	9	localObject4	Object
      //   21	478	10	localb	b.i.b.a.c.g.d.b
      //   29	451	11	localf	f
      // Exception table:
      //   from	to	target	type
      //   39	44	412	finally
      //   84	96	412	finally
      //   99	104	412	finally
      //   117	126	412	finally
      //   126	141	412	finally
      //   146	165	412	finally
      //   165	170	412	finally
      //   170	178	412	finally
      //   181	186	412	finally
      //   200	209	412	finally
      //   209	224	412	finally
      //   229	248	412	finally
      //   248	253	412	finally
      //   256	261	412	finally
      //   275	284	412	finally
      //   284	299	412	finally
      //   304	323	412	finally
      //   323	328	412	finally
      //   335	354	412	finally
      //   354	369	412	finally
      //   374	393	412	finally
      //   393	403	412	finally
      //   417	436	412	finally
      //   437	444	412	finally
      //   39	44	416	java/io/IOException
      //   84	96	416	java/io/IOException
      //   99	104	416	java/io/IOException
      //   117	126	416	java/io/IOException
      //   126	141	416	java/io/IOException
      //   146	165	416	java/io/IOException
      //   165	170	416	java/io/IOException
      //   170	178	416	java/io/IOException
      //   181	186	416	java/io/IOException
      //   200	209	416	java/io/IOException
      //   209	224	416	java/io/IOException
      //   229	248	416	java/io/IOException
      //   248	253	416	java/io/IOException
      //   256	261	416	java/io/IOException
      //   275	284	416	java/io/IOException
      //   284	299	416	java/io/IOException
      //   304	323	416	java/io/IOException
      //   323	328	416	java/io/IOException
      //   335	354	416	java/io/IOException
      //   354	369	416	java/io/IOException
      //   374	393	416	java/io/IOException
      //   393	403	416	java/io/IOException
      //   39	44	436	b/i/b/a/c/g/k
      //   84	96	436	b/i/b/a/c/g/k
      //   99	104	436	b/i/b/a/c/g/k
      //   117	126	436	b/i/b/a/c/g/k
      //   126	141	436	b/i/b/a/c/g/k
      //   146	165	436	b/i/b/a/c/g/k
      //   165	170	436	b/i/b/a/c/g/k
      //   170	178	436	b/i/b/a/c/g/k
      //   181	186	436	b/i/b/a/c/g/k
      //   200	209	436	b/i/b/a/c/g/k
      //   209	224	436	b/i/b/a/c/g/k
      //   229	248	436	b/i/b/a/c/g/k
      //   248	253	436	b/i/b/a/c/g/k
      //   256	261	436	b/i/b/a/c/g/k
      //   275	284	436	b/i/b/a/c/g/k
      //   284	299	436	b/i/b/a/c/g/k
      //   304	323	436	b/i/b/a/c/g/k
      //   323	328	436	b/i/b/a/c/g/k
      //   335	354	436	b/i/b/a/c/g/k
      //   354	369	436	b/i/b/a/c/g/k
      //   374	393	436	b/i/b/a/c/g/k
      //   393	403	436	b/i/b/a/c/g/k
      //   444	449	461	finally
      //   479	484	496	finally
      //   444	449	513	java/io/IOException
      //   479	484	517	java/io/IOException
    }
    
    private e(i.a parama)
    {
      super();
      this.g = parama.a;
    }
    
    public static e a()
    {
      return f;
    }
    
    private void l()
    {
      this.b = b.a.a();
      this.c = b.c.a();
      this.d = b.c.a();
      this.e = b.c.a();
    }
    
    public final void a(f paramf)
      throws IOException
    {
      f();
      if ((this.h & 0x1) == 1) {
        paramf.a(1, this.b);
      }
      if ((this.h & 0x2) == 2) {
        paramf.a(2, this.c);
      }
      if ((this.h & 0x4) == 4) {
        paramf.a(3, this.d);
      }
      if ((this.h & 0x8) == 8) {
        paramf.a(4, this.e);
      }
      paramf.c(this.g);
    }
    
    public final s<e> b()
    {
      return a;
    }
    
    public final boolean c()
    {
      return (this.h & 0x1) == 1;
    }
    
    public final boolean d()
    {
      return (this.h & 0x2) == 2;
    }
    
    public final boolean e()
    {
      int k = this.i;
      if (k == 1) {
        return true;
      }
      if (k == 0) {
        return false;
      }
      this.i = 1;
      return true;
    }
    
    public final int f()
    {
      int k = this.j;
      if (k != -1) {
        return k;
      }
      int m = this.h;
      k = 0;
      if ((m & 0x1) == 1) {
        k = 0 + f.c(1, this.b);
      }
      m = k;
      if ((this.h & 0x2) == 2) {
        m = k + f.c(2, this.c);
      }
      k = m;
      if ((this.h & 0x4) == 4) {
        k = m + f.c(3, this.d);
      }
      m = k;
      if ((this.h & 0x8) == 8) {
        m = k + f.c(4, this.e);
      }
      k = m + this.g.a();
      this.j = k;
      return k;
    }
    
    public final boolean g()
    {
      return (this.h & 0x4) == 4;
    }
    
    public final boolean k()
    {
      return (this.h & 0x8) == 8;
    }
    
    public static final class a
      extends i.a<b.e, a>
      implements b.f
    {
      private int b;
      private b.a c = b.a.a();
      private b.c d = b.c.a();
      private b.c e = b.c.a();
      private b.c f = b.c.a();
      
      private a a(b.a parama)
      {
        b.a locala = parama;
        if ((this.b & 0x1) == 1)
        {
          locala = parama;
          if (this.c != b.a.a()) {
            locala = b.a.a(this.c).a(parama).f();
          }
        }
        this.c = locala;
        this.b |= 0x1;
        return this;
      }
      
      private a a(b.c paramc)
      {
        b.c localc = paramc;
        if ((this.b & 0x2) == 2)
        {
          localc = paramc;
          if (this.d != b.c.a()) {
            localc = b.c.a(this.d).a(paramc).f();
          }
        }
        this.d = localc;
        this.b |= 0x2;
        return this;
      }
      
      private a b(b.c paramc)
      {
        b.c localc = paramc;
        if ((this.b & 0x4) == 4)
        {
          localc = paramc;
          if (this.e != b.c.a()) {
            localc = b.c.a(this.e).a(paramc).f();
          }
        }
        this.e = localc;
        this.b |= 0x4;
        return this;
      }
      
      private a c(b.c paramc)
      {
        b.c localc = paramc;
        if ((this.b & 0x8) == 8)
        {
          localc = paramc;
          if (this.f != b.c.a()) {
            localc = b.c.a(this.f).a(paramc).f();
          }
        }
        this.f = localc;
        this.b |= 0x8;
        return this;
      }
      
      /* Error */
      private a c(b.i.b.a.c.g.e parame, g paramg)
        throws IOException
      {
        // Byte code:
        //   0: aconst_null
        //   1: astore_3
        //   2: getstatic 71	b/i/b/a/c/e/b/b$e:a	Lb/i/b/a/c/g/s;
        //   5: aload_1
        //   6: aload_2
        //   7: invokeinterface 76 3 0
        //   12: checkcast 9	b/i/b/a/c/e/b/b$e
        //   15: astore_1
        //   16: aload_0
        //   17: aload_1
        //   18: invokevirtual 79	b/i/b/a/c/e/b/b$e$a:a	(Lb/i/b/a/c/e/b/b$e;)Lb/i/b/a/c/e/b/b$e$a;
        //   21: pop
        //   22: aload_0
        //   23: areturn
        //   24: astore_2
        //   25: aload_3
        //   26: astore_1
        //   27: goto +15 -> 42
        //   30: astore_2
        //   31: aload_2
        //   32: getfield 82	b/i/b/a/c/g/k:a	Lb/i/b/a/c/g/q;
        //   35: checkcast 9	b/i/b/a/c/e/b/b$e
        //   38: astore_1
        //   39: aload_2
        //   40: athrow
        //   41: astore_2
        //   42: aload_1
        //   43: ifnull +9 -> 52
        //   46: aload_0
        //   47: aload_1
        //   48: invokevirtual 79	b/i/b/a/c/e/b/b$e$a:a	(Lb/i/b/a/c/e/b/b$e;)Lb/i/b/a/c/e/b/b$e$a;
        //   51: pop
        //   52: aload_2
        //   53: athrow
        // Local variable table:
        //   start	length	slot	name	signature
        //   0	54	0	this	a
        //   0	54	1	parame	b.i.b.a.c.g.e
        //   0	54	2	paramg	g
        //   1	25	3	localObject	Object
        // Exception table:
        //   from	to	target	type
        //   2	16	24	finally
        //   31	39	24	finally
        //   2	16	30	b/i/b/a/c/g/k
        //   39	41	41	finally
      }
      
      private a g()
      {
        return new a().a(h());
      }
      
      private b.e h()
      {
        int j = 0;
        b.e locale = new b.e(this, (byte)0);
        int k = this.b;
        if ((k & 0x1) == 1) {
          j = 1;
        }
        b.e.a(locale, this.c);
        int i = j;
        if ((k & 0x2) == 2) {
          i = j | 0x2;
        }
        b.e.a(locale, this.d);
        j = i;
        if ((k & 0x4) == 4) {
          j = i | 0x4;
        }
        b.e.b(locale, this.e);
        i = j;
        if ((k & 0x8) == 8) {
          i = j | 0x8;
        }
        b.e.c(locale, this.f);
        b.e.a(locale, i);
        return locale;
      }
      
      public final a a(b.e parame)
      {
        if (parame == b.e.a()) {
          return this;
        }
        if (parame.c()) {
          a(parame.b);
        }
        if (parame.d()) {
          a(parame.c);
        }
        if (parame.g()) {
          b(parame.d);
        }
        if (parame.k()) {
          c(parame.e);
        }
        this.a = this.a.a(b.e.a(parame));
        return this;
      }
      
      public final boolean e()
      {
        return true;
      }
    }
  }
  
  public static abstract interface f
    extends r
  {}
  
  public static final class g
    extends i
    implements b.h
  {
    public static s<g> a = new b.i.b.a.c.g.b() {};
    private static final g d;
    public List<b> b;
    public List<Integer> c;
    private final d e;
    private int f = -1;
    private byte g = -1;
    private int h = -1;
    
    static
    {
      g localg = new g();
      d = localg;
      localg.c();
    }
    
    private g()
    {
      this.e = d.b;
    }
    
    /* Error */
    private g(b.i.b.a.c.g.e parame, g paramg)
      throws b.i.b.a.c.g.k
    {
      // Byte code:
      //   0: aload_0
      //   1: invokespecial 55	b/i/b/a/c/g/i:<init>	()V
      //   4: aload_0
      //   5: iconst_m1
      //   6: putfield 57	b/i/b/a/c/e/b/b$g:f	I
      //   9: aload_0
      //   10: iconst_m1
      //   11: putfield 59	b/i/b/a/c/e/b/b$g:g	B
      //   14: aload_0
      //   15: iconst_m1
      //   16: putfield 61	b/i/b/a/c/e/b/b$g:h	I
      //   19: aload_0
      //   20: invokespecial 53	b/i/b/a/c/e/b/b$g:c	()V
      //   23: invokestatic 75	b/i/b/a/c/g/d:h	()Lb/i/b/a/c/g/d$b;
      //   26: astore 12
      //   28: aload 12
      //   30: iconst_1
      //   31: invokestatic 80	b/i/b/a/c/g/f:a	(Ljava/io/OutputStream;I)Lb/i/b/a/c/g/f;
      //   34: astore 13
      //   36: iconst_0
      //   37: istore 8
      //   39: iconst_0
      //   40: istore_3
      //   41: iload 8
      //   43: ifne +528 -> 571
      //   46: iload_3
      //   47: istore 4
      //   49: iload_3
      //   50: istore 5
      //   52: iload_3
      //   53: istore 6
      //   55: aload_1
      //   56: invokevirtual 85	b/i/b/a/c/g/e:a	()I
      //   59: istore 7
      //   61: iload 7
      //   63: ifeq +377 -> 440
      //   66: iload 7
      //   68: bipush 10
      //   70: if_icmpeq +289 -> 359
      //   73: iload 7
      //   75: bipush 40
      //   77: if_icmpeq +183 -> 260
      //   80: iload 7
      //   82: bipush 42
      //   84: if_icmpeq +28 -> 112
      //   87: iload_3
      //   88: istore 4
      //   90: iload_3
      //   91: istore 5
      //   93: iload_3
      //   94: istore 6
      //   96: aload_0
      //   97: aload_1
      //   98: aload 13
      //   100: aload_2
      //   101: iload 7
      //   103: invokevirtual 88	b/i/b/a/c/e/b/b$g:a	(Lb/i/b/a/c/g/e;Lb/i/b/a/c/g/f;Lb/i/b/a/c/g/g;I)Z
      //   106: ifne -65 -> 41
      //   109: goto +331 -> 440
      //   112: iload_3
      //   113: istore 4
      //   115: iload_3
      //   116: istore 5
      //   118: iload_3
      //   119: istore 6
      //   121: aload_1
      //   122: aload_1
      //   123: invokevirtual 90	b/i/b/a/c/g/e:d	()I
      //   126: invokevirtual 93	b/i/b/a/c/g/e:b	(I)I
      //   129: istore 9
      //   131: iload_3
      //   132: istore 7
      //   134: iload_3
      //   135: iconst_2
      //   136: iand
      //   137: iconst_2
      //   138: if_icmpeq +47 -> 185
      //   141: iload_3
      //   142: istore 7
      //   144: iload_3
      //   145: istore 4
      //   147: iload_3
      //   148: istore 5
      //   150: iload_3
      //   151: istore 6
      //   153: aload_1
      //   154: invokevirtual 95	b/i/b/a/c/g/e:h	()I
      //   157: ifle +28 -> 185
      //   160: iload_3
      //   161: istore 4
      //   163: iload_3
      //   164: istore 5
      //   166: iload_3
      //   167: istore 6
      //   169: aload_0
      //   170: new 97	java/util/ArrayList
      //   173: dup
      //   174: invokespecial 98	java/util/ArrayList:<init>	()V
      //   177: putfield 100	b/i/b/a/c/e/b/b$g:c	Ljava/util/List;
      //   180: iload_3
      //   181: iconst_2
      //   182: ior
      //   183: istore 7
      //   185: iload 7
      //   187: istore 4
      //   189: iload 7
      //   191: istore 5
      //   193: iload 7
      //   195: istore 6
      //   197: aload_1
      //   198: invokevirtual 95	b/i/b/a/c/g/e:h	()I
      //   201: ifle +35 -> 236
      //   204: iload 7
      //   206: istore 4
      //   208: iload 7
      //   210: istore 5
      //   212: iload 7
      //   214: istore 6
      //   216: aload_0
      //   217: getfield 100	b/i/b/a/c/e/b/b$g:c	Ljava/util/List;
      //   220: aload_1
      //   221: invokevirtual 90	b/i/b/a/c/g/e:d	()I
      //   224: invokestatic 106	java/lang/Integer:valueOf	(I)Ljava/lang/Integer;
      //   227: invokeinterface 112 2 0
      //   232: pop
      //   233: goto -48 -> 185
      //   236: iload 7
      //   238: istore 4
      //   240: iload 7
      //   242: istore 5
      //   244: iload 7
      //   246: istore 6
      //   248: aload_1
      //   249: iload 9
      //   251: invokevirtual 115	b/i/b/a/c/g/e:c	(I)V
      //   254: iload 7
      //   256: istore_3
      //   257: goto -216 -> 41
      //   260: iload_3
      //   261: istore 7
      //   263: iload_3
      //   264: iconst_2
      //   265: iand
      //   266: iconst_2
      //   267: if_icmpeq +28 -> 295
      //   270: iload_3
      //   271: istore 4
      //   273: iload_3
      //   274: istore 5
      //   276: iload_3
      //   277: istore 6
      //   279: aload_0
      //   280: new 97	java/util/ArrayList
      //   283: dup
      //   284: invokespecial 98	java/util/ArrayList:<init>	()V
      //   287: putfield 100	b/i/b/a/c/e/b/b$g:c	Ljava/util/List;
      //   290: iload_3
      //   291: iconst_2
      //   292: ior
      //   293: istore 7
      //   295: iload 7
      //   297: istore 4
      //   299: iload 7
      //   301: istore 5
      //   303: iload 7
      //   305: istore 6
      //   307: aload_0
      //   308: getfield 100	b/i/b/a/c/e/b/b$g:c	Ljava/util/List;
      //   311: astore 10
      //   313: iload 7
      //   315: istore 4
      //   317: iload 7
      //   319: istore 5
      //   321: iload 7
      //   323: istore 6
      //   325: aload_1
      //   326: invokevirtual 90	b/i/b/a/c/g/e:d	()I
      //   329: invokestatic 106	java/lang/Integer:valueOf	(I)Ljava/lang/Integer;
      //   332: astore 11
      //   334: iload 7
      //   336: istore_3
      //   337: iload_3
      //   338: istore 4
      //   340: iload_3
      //   341: istore 5
      //   343: iload_3
      //   344: istore 6
      //   346: aload 10
      //   348: aload 11
      //   350: invokeinterface 112 2 0
      //   355: pop
      //   356: goto -315 -> 41
      //   359: iload_3
      //   360: istore 7
      //   362: iload_3
      //   363: iconst_1
      //   364: iand
      //   365: iconst_1
      //   366: if_icmpeq +28 -> 394
      //   369: iload_3
      //   370: istore 4
      //   372: iload_3
      //   373: istore 5
      //   375: iload_3
      //   376: istore 6
      //   378: aload_0
      //   379: new 97	java/util/ArrayList
      //   382: dup
      //   383: invokespecial 98	java/util/ArrayList:<init>	()V
      //   386: putfield 117	b/i/b/a/c/e/b/b$g:b	Ljava/util/List;
      //   389: iload_3
      //   390: iconst_1
      //   391: ior
      //   392: istore 7
      //   394: iload 7
      //   396: istore 4
      //   398: iload 7
      //   400: istore 5
      //   402: iload 7
      //   404: istore 6
      //   406: aload_0
      //   407: getfield 117	b/i/b/a/c/e/b/b$g:b	Ljava/util/List;
      //   410: astore 10
      //   412: iload 7
      //   414: istore 4
      //   416: iload 7
      //   418: istore 5
      //   420: iload 7
      //   422: istore 6
      //   424: aload_1
      //   425: getstatic 118	b/i/b/a/c/e/b/b$g$b:a	Lb/i/b/a/c/g/s;
      //   428: aload_2
      //   429: invokevirtual 121	b/i/b/a/c/g/e:a	(Lb/i/b/a/c/g/s;Lb/i/b/a/c/g/g;)Lb/i/b/a/c/g/q;
      //   432: astore 11
      //   434: iload 7
      //   436: istore_3
      //   437: goto -100 -> 337
      //   440: iconst_1
      //   441: istore 8
      //   443: goto -402 -> 41
      //   446: astore_1
      //   447: goto +51 -> 498
      //   450: astore_1
      //   451: iload 5
      //   453: istore 4
      //   455: new 70	b/i/b/a/c/g/k
      //   458: dup
      //   459: aload_1
      //   460: invokevirtual 125	java/io/IOException:getMessage	()Ljava/lang/String;
      //   463: invokespecial 128	b/i/b/a/c/g/k:<init>	(Ljava/lang/String;)V
      //   466: astore_1
      //   467: iload 5
      //   469: istore 4
      //   471: aload_1
      //   472: aload_0
      //   473: putfield 131	b/i/b/a/c/g/k:a	Lb/i/b/a/c/g/q;
      //   476: iload 5
      //   478: istore 4
      //   480: aload_1
      //   481: athrow
      //   482: astore_1
      //   483: iload 6
      //   485: istore 4
      //   487: aload_1
      //   488: aload_0
      //   489: putfield 131	b/i/b/a/c/g/k:a	Lb/i/b/a/c/g/q;
      //   492: iload 6
      //   494: istore 4
      //   496: aload_1
      //   497: athrow
      //   498: iload 4
      //   500: iconst_1
      //   501: iand
      //   502: iconst_1
      //   503: if_icmpne +14 -> 517
      //   506: aload_0
      //   507: aload_0
      //   508: getfield 117	b/i/b/a/c/e/b/b$g:b	Ljava/util/List;
      //   511: invokestatic 137	java/util/Collections:unmodifiableList	(Ljava/util/List;)Ljava/util/List;
      //   514: putfield 117	b/i/b/a/c/e/b/b$g:b	Ljava/util/List;
      //   517: iload 4
      //   519: iconst_2
      //   520: iand
      //   521: iconst_2
      //   522: if_icmpne +14 -> 536
      //   525: aload_0
      //   526: aload_0
      //   527: getfield 100	b/i/b/a/c/e/b/b$g:c	Ljava/util/List;
      //   530: invokestatic 137	java/util/Collections:unmodifiableList	(Ljava/util/List;)Ljava/util/List;
      //   533: putfield 100	b/i/b/a/c/e/b/b$g:c	Ljava/util/List;
      //   536: aload 13
      //   538: invokevirtual 139	b/i/b/a/c/g/f:a	()V
      //   541: aload_0
      //   542: aload 12
      //   544: invokevirtual 144	b/i/b/a/c/g/d$b:a	()Lb/i/b/a/c/g/d;
      //   547: putfield 67	b/i/b/a/c/e/b/b$g:e	Lb/i/b/a/c/g/d;
      //   550: goto +15 -> 565
      //   553: astore_1
      //   554: aload_0
      //   555: aload 12
      //   557: invokevirtual 144	b/i/b/a/c/g/d$b:a	()Lb/i/b/a/c/g/d;
      //   560: putfield 67	b/i/b/a/c/e/b/b$g:e	Lb/i/b/a/c/g/d;
      //   563: aload_1
      //   564: athrow
      //   565: aload_0
      //   566: invokevirtual 147	b/i/b/a/c/e/b/b$g:w	()V
      //   569: aload_1
      //   570: athrow
      //   571: iload_3
      //   572: iconst_1
      //   573: iand
      //   574: iconst_1
      //   575: if_icmpne +14 -> 589
      //   578: aload_0
      //   579: aload_0
      //   580: getfield 117	b/i/b/a/c/e/b/b$g:b	Ljava/util/List;
      //   583: invokestatic 137	java/util/Collections:unmodifiableList	(Ljava/util/List;)Ljava/util/List;
      //   586: putfield 117	b/i/b/a/c/e/b/b$g:b	Ljava/util/List;
      //   589: iload_3
      //   590: iconst_2
      //   591: iand
      //   592: iconst_2
      //   593: if_icmpne +14 -> 607
      //   596: aload_0
      //   597: aload_0
      //   598: getfield 100	b/i/b/a/c/e/b/b$g:c	Ljava/util/List;
      //   601: invokestatic 137	java/util/Collections:unmodifiableList	(Ljava/util/List;)Ljava/util/List;
      //   604: putfield 100	b/i/b/a/c/e/b/b$g:c	Ljava/util/List;
      //   607: aload 13
      //   609: invokevirtual 139	b/i/b/a/c/g/f:a	()V
      //   612: aload_0
      //   613: aload 12
      //   615: invokevirtual 144	b/i/b/a/c/g/d$b:a	()Lb/i/b/a/c/g/d;
      //   618: putfield 67	b/i/b/a/c/e/b/b$g:e	Lb/i/b/a/c/g/d;
      //   621: goto +15 -> 636
      //   624: astore_1
      //   625: aload_0
      //   626: aload 12
      //   628: invokevirtual 144	b/i/b/a/c/g/d$b:a	()Lb/i/b/a/c/g/d;
      //   631: putfield 67	b/i/b/a/c/e/b/b$g:e	Lb/i/b/a/c/g/d;
      //   634: aload_1
      //   635: athrow
      //   636: aload_0
      //   637: invokevirtual 147	b/i/b/a/c/e/b/b$g:w	()V
      //   640: return
      //   641: astore_2
      //   642: goto -101 -> 541
      //   645: astore_1
      //   646: goto -34 -> 612
      // Local variable table:
      //   start	length	slot	name	signature
      //   0	649	0	this	g
      //   0	649	1	parame	b.i.b.a.c.g.e
      //   0	649	2	paramg	g
      //   40	552	3	i	int
      //   47	474	4	j	int
      //   50	427	5	k	int
      //   53	440	6	m	int
      //   59	376	7	n	int
      //   37	405	8	i1	int
      //   129	121	9	i2	int
      //   311	100	10	localList	List
      //   332	101	11	localObject	Object
      //   26	601	12	localb	b.i.b.a.c.g.d.b
      //   34	574	13	localf	f
      // Exception table:
      //   from	to	target	type
      //   55	61	446	finally
      //   96	109	446	finally
      //   121	131	446	finally
      //   153	160	446	finally
      //   169	180	446	finally
      //   197	204	446	finally
      //   216	233	446	finally
      //   248	254	446	finally
      //   279	290	446	finally
      //   307	313	446	finally
      //   325	334	446	finally
      //   346	356	446	finally
      //   378	389	446	finally
      //   406	412	446	finally
      //   424	434	446	finally
      //   455	467	446	finally
      //   471	476	446	finally
      //   480	482	446	finally
      //   487	492	446	finally
      //   496	498	446	finally
      //   55	61	450	java/io/IOException
      //   96	109	450	java/io/IOException
      //   121	131	450	java/io/IOException
      //   153	160	450	java/io/IOException
      //   169	180	450	java/io/IOException
      //   197	204	450	java/io/IOException
      //   216	233	450	java/io/IOException
      //   248	254	450	java/io/IOException
      //   279	290	450	java/io/IOException
      //   307	313	450	java/io/IOException
      //   325	334	450	java/io/IOException
      //   346	356	450	java/io/IOException
      //   378	389	450	java/io/IOException
      //   406	412	450	java/io/IOException
      //   424	434	450	java/io/IOException
      //   55	61	482	b/i/b/a/c/g/k
      //   96	109	482	b/i/b/a/c/g/k
      //   121	131	482	b/i/b/a/c/g/k
      //   153	160	482	b/i/b/a/c/g/k
      //   169	180	482	b/i/b/a/c/g/k
      //   197	204	482	b/i/b/a/c/g/k
      //   216	233	482	b/i/b/a/c/g/k
      //   248	254	482	b/i/b/a/c/g/k
      //   279	290	482	b/i/b/a/c/g/k
      //   307	313	482	b/i/b/a/c/g/k
      //   325	334	482	b/i/b/a/c/g/k
      //   346	356	482	b/i/b/a/c/g/k
      //   378	389	482	b/i/b/a/c/g/k
      //   406	412	482	b/i/b/a/c/g/k
      //   424	434	482	b/i/b/a/c/g/k
      //   536	541	553	finally
      //   607	612	624	finally
      //   536	541	641	java/io/IOException
      //   607	612	645	java/io/IOException
    }
    
    private g(i.a parama)
    {
      super();
      this.e = parama.a;
    }
    
    public static g a()
    {
      return d;
    }
    
    public static g a(InputStream paramInputStream, g paramg)
      throws IOException
    {
      return (g)a.a(paramInputStream, paramg);
    }
    
    private void c()
    {
      this.b = Collections.emptyList();
      this.c = Collections.emptyList();
    }
    
    public final void a(f paramf)
      throws IOException
    {
      f();
      int j = 0;
      int i = 0;
      while (i < this.b.size())
      {
        paramf.a(1, (q)this.b.get(i));
        i += 1;
      }
      i = j;
      if (this.c.size() > 0)
      {
        paramf.e(42);
        paramf.e(this.f);
        i = j;
      }
      while (i < this.c.size())
      {
        paramf.a(((Integer)this.c.get(i)).intValue());
        i += 1;
      }
      paramf.c(this.e);
    }
    
    public final s<g> b()
    {
      return a;
    }
    
    public final boolean e()
    {
      int i = this.g;
      if (i == 1) {
        return true;
      }
      if (i == 0) {
        return false;
      }
      this.g = 1;
      return true;
    }
    
    public final int f()
    {
      int i = this.h;
      if (i != -1) {
        return i;
      }
      int k = 0;
      int j = 0;
      i = 0;
      while (j < this.b.size())
      {
        i += f.c(1, (q)this.b.get(j));
        j += 1;
      }
      j = 0;
      while (k < this.c.size())
      {
        j += f.c(((Integer)this.c.get(k)).intValue());
        k += 1;
      }
      k = i + j;
      i = k;
      if (!this.c.isEmpty()) {
        i = k + 1 + f.c(j);
      }
      this.f = j;
      i += this.e.a();
      this.h = i;
      return i;
    }
    
    public static final class a
      extends i.a<b.g, a>
      implements b.h
    {
      private int b;
      private List<b.g.b> c = Collections.emptyList();
      private List<Integer> d = Collections.emptyList();
      
      /* Error */
      private a c(b.i.b.a.c.g.e parame, g paramg)
        throws IOException
      {
        // Byte code:
        //   0: aconst_null
        //   1: astore_3
        //   2: getstatic 43	b/i/b/a/c/e/b/b$g:a	Lb/i/b/a/c/g/s;
        //   5: aload_1
        //   6: aload_2
        //   7: invokeinterface 48 3 0
        //   12: checkcast 9	b/i/b/a/c/e/b/b$g
        //   15: astore_1
        //   16: aload_0
        //   17: aload_1
        //   18: invokevirtual 51	b/i/b/a/c/e/b/b$g$a:a	(Lb/i/b/a/c/e/b/b$g;)Lb/i/b/a/c/e/b/b$g$a;
        //   21: pop
        //   22: aload_0
        //   23: areturn
        //   24: astore_2
        //   25: aload_3
        //   26: astore_1
        //   27: goto +15 -> 42
        //   30: astore_2
        //   31: aload_2
        //   32: getfield 54	b/i/b/a/c/g/k:a	Lb/i/b/a/c/g/q;
        //   35: checkcast 9	b/i/b/a/c/e/b/b$g
        //   38: astore_1
        //   39: aload_2
        //   40: athrow
        //   41: astore_2
        //   42: aload_1
        //   43: ifnull +9 -> 52
        //   46: aload_0
        //   47: aload_1
        //   48: invokevirtual 51	b/i/b/a/c/e/b/b$g$a:a	(Lb/i/b/a/c/e/b/b$g;)Lb/i/b/a/c/e/b/b$g$a;
        //   51: pop
        //   52: aload_2
        //   53: athrow
        // Local variable table:
        //   start	length	slot	name	signature
        //   0	54	0	this	a
        //   0	54	1	parame	b.i.b.a.c.g.e
        //   0	54	2	paramg	g
        //   1	25	3	localObject	Object
        // Exception table:
        //   from	to	target	type
        //   2	16	24	finally
        //   31	39	24	finally
        //   2	16	30	b/i/b/a/c/g/k
        //   39	41	41	finally
      }
      
      private a g()
      {
        return new a().a(h());
      }
      
      private b.g h()
      {
        b.g localg = new b.g(this, (byte)0);
        if ((this.b & 0x1) == 1)
        {
          this.c = Collections.unmodifiableList(this.c);
          this.b &= 0xFFFFFFFE;
        }
        b.g.a(localg, this.c);
        if ((this.b & 0x2) == 2)
        {
          this.d = Collections.unmodifiableList(this.d);
          this.b &= 0xFFFFFFFD;
        }
        b.g.b(localg, this.d);
        return localg;
      }
      
      private void i()
      {
        if ((this.b & 0x1) != 1)
        {
          this.c = new ArrayList(this.c);
          this.b |= 0x1;
        }
      }
      
      private void k()
      {
        if ((this.b & 0x2) != 2)
        {
          this.d = new ArrayList(this.d);
          this.b |= 0x2;
        }
      }
      
      public final a a(b.g paramg)
      {
        if (paramg == b.g.a()) {
          return this;
        }
        if (!b.g.a(paramg).isEmpty()) {
          if (this.c.isEmpty())
          {
            this.c = b.g.a(paramg);
            this.b &= 0xFFFFFFFE;
          }
          else
          {
            i();
            this.c.addAll(b.g.a(paramg));
          }
        }
        if (!b.g.b(paramg).isEmpty()) {
          if (this.d.isEmpty())
          {
            this.d = b.g.b(paramg);
            this.b &= 0xFFFFFFFD;
          }
          else
          {
            k();
            this.d.addAll(b.g.b(paramg));
          }
        }
        this.a = this.a.a(b.g.c(paramg));
        return this;
      }
      
      public final boolean e()
      {
        return true;
      }
    }
    
    public static final class b
      extends i
      implements b.g.c
    {
      public static s<b> a = new b.i.b.a.c.g.b() {};
      private static final b g;
      public int b;
      public int c;
      public b d;
      public List<Integer> e;
      public List<Integer> f;
      private final d h;
      private int i;
      private Object j;
      private int k = -1;
      private int l = -1;
      private byte m = -1;
      private int n = -1;
      
      static
      {
        b localb = new b();
        g = localb;
        localb.p();
      }
      
      private b()
      {
        this.h = d.b;
      }
      
      /* Error */
      private b(b.i.b.a.c.g.e parame, g paramg)
        throws b.i.b.a.c.g.k
      {
        // Byte code:
        //   0: aload_0
        //   1: invokespecial 57	b/i/b/a/c/g/i:<init>	()V
        //   4: aload_0
        //   5: iconst_m1
        //   6: putfield 59	b/i/b/a/c/e/b/b$g$b:k	I
        //   9: aload_0
        //   10: iconst_m1
        //   11: putfield 61	b/i/b/a/c/e/b/b$g$b:l	I
        //   14: aload_0
        //   15: iconst_m1
        //   16: putfield 63	b/i/b/a/c/e/b/b$g$b:m	B
        //   19: aload_0
        //   20: iconst_m1
        //   21: putfield 65	b/i/b/a/c/e/b/b$g$b:n	I
        //   24: aload_0
        //   25: invokespecial 55	b/i/b/a/c/e/b/b$g$b:p	()V
        //   28: invokestatic 79	b/i/b/a/c/g/d:h	()Lb/i/b/a/c/g/d$b;
        //   31: astore 13
        //   33: aload 13
        //   35: iconst_1
        //   36: invokestatic 84	b/i/b/a/c/g/f:a	(Ljava/io/OutputStream;I)Lb/i/b/a/c/g/f;
        //   39: astore 14
        //   41: iconst_0
        //   42: istore 8
        //   44: iconst_0
        //   45: istore_3
        //   46: iload 8
        //   48: ifne +949 -> 997
        //   51: iload_3
        //   52: istore 4
        //   54: iload_3
        //   55: istore 5
        //   57: iload_3
        //   58: istore 6
        //   60: aload_1
        //   61: invokevirtual 89	b/i/b/a/c/g/e:a	()I
        //   64: istore 7
        //   66: iload 7
        //   68: ifeq +794 -> 862
        //   71: iload 7
        //   73: bipush 8
        //   75: if_icmpeq +748 -> 823
        //   78: iload 7
        //   80: bipush 16
        //   82: if_icmpeq +702 -> 784
        //   85: iload 7
        //   87: bipush 24
        //   89: if_icmpeq +586 -> 675
        //   92: iload 7
        //   94: bipush 32
        //   96: if_icmpeq +496 -> 592
        //   99: iload 7
        //   101: bipush 34
        //   103: if_icmpeq +355 -> 458
        //   106: iload 7
        //   108: bipush 40
        //   110: if_icmpeq +246 -> 356
        //   113: iload 7
        //   115: bipush 42
        //   117: if_icmpeq +87 -> 204
        //   120: iload 7
        //   122: bipush 50
        //   124: if_icmpeq +28 -> 152
        //   127: iload_3
        //   128: istore 4
        //   130: iload_3
        //   131: istore 5
        //   133: iload_3
        //   134: istore 6
        //   136: aload_0
        //   137: aload_1
        //   138: aload 14
        //   140: aload_2
        //   141: iload 7
        //   143: invokevirtual 92	b/i/b/a/c/e/b/b$g$b:a	(Lb/i/b/a/c/g/e;Lb/i/b/a/c/g/f;Lb/i/b/a/c/g/g;I)Z
        //   146: ifne -100 -> 46
        //   149: goto +713 -> 862
        //   152: iload_3
        //   153: istore 4
        //   155: iload_3
        //   156: istore 5
        //   158: iload_3
        //   159: istore 6
        //   161: aload_1
        //   162: invokevirtual 95	b/i/b/a/c/g/e:c	()Lb/i/b/a/c/g/d;
        //   165: astore 11
        //   167: iload_3
        //   168: istore 4
        //   170: iload_3
        //   171: istore 5
        //   173: iload_3
        //   174: istore 6
        //   176: aload_0
        //   177: aload_0
        //   178: getfield 97	b/i/b/a/c/e/b/b$g$b:i	I
        //   181: iconst_4
        //   182: ior
        //   183: putfield 97	b/i/b/a/c/e/b/b$g$b:i	I
        //   186: iload_3
        //   187: istore 4
        //   189: iload_3
        //   190: istore 5
        //   192: iload_3
        //   193: istore 6
        //   195: aload_0
        //   196: aload 11
        //   198: putfield 99	b/i/b/a/c/e/b/b$g$b:j	Ljava/lang/Object;
        //   201: goto -155 -> 46
        //   204: iload_3
        //   205: istore 4
        //   207: iload_3
        //   208: istore 5
        //   210: iload_3
        //   211: istore 6
        //   213: aload_1
        //   214: aload_1
        //   215: invokevirtual 101	b/i/b/a/c/g/e:d	()I
        //   218: invokevirtual 104	b/i/b/a/c/g/e:b	(I)I
        //   221: istore 10
        //   223: iload_3
        //   224: istore 7
        //   226: iload_3
        //   227: bipush 32
        //   229: iand
        //   230: bipush 32
        //   232: if_icmpeq +48 -> 280
        //   235: iload_3
        //   236: istore 7
        //   238: iload_3
        //   239: istore 4
        //   241: iload_3
        //   242: istore 5
        //   244: iload_3
        //   245: istore 6
        //   247: aload_1
        //   248: invokevirtual 106	b/i/b/a/c/g/e:h	()I
        //   251: ifle +29 -> 280
        //   254: iload_3
        //   255: istore 4
        //   257: iload_3
        //   258: istore 5
        //   260: iload_3
        //   261: istore 6
        //   263: aload_0
        //   264: new 108	java/util/ArrayList
        //   267: dup
        //   268: invokespecial 109	java/util/ArrayList:<init>	()V
        //   271: putfield 111	b/i/b/a/c/e/b/b$g$b:f	Ljava/util/List;
        //   274: iload_3
        //   275: bipush 32
        //   277: ior
        //   278: istore 7
        //   280: iload 7
        //   282: istore_3
        //   283: iload 10
        //   285: istore 9
        //   287: iload 7
        //   289: istore 4
        //   291: iload 7
        //   293: istore 5
        //   295: iload 7
        //   297: istore 6
        //   299: aload_1
        //   300: invokevirtual 106	b/i/b/a/c/g/e:h	()I
        //   303: ifle +35 -> 338
        //   306: iload 7
        //   308: istore 4
        //   310: iload 7
        //   312: istore 5
        //   314: iload 7
        //   316: istore 6
        //   318: aload_0
        //   319: getfield 111	b/i/b/a/c/e/b/b$g$b:f	Ljava/util/List;
        //   322: aload_1
        //   323: invokevirtual 101	b/i/b/a/c/g/e:d	()I
        //   326: invokestatic 117	java/lang/Integer:valueOf	(I)Ljava/lang/Integer;
        //   329: invokeinterface 123 2 0
        //   334: pop
        //   335: goto -55 -> 280
        //   338: iload_3
        //   339: istore 4
        //   341: iload_3
        //   342: istore 5
        //   344: iload_3
        //   345: istore 6
        //   347: aload_1
        //   348: iload 9
        //   350: invokevirtual 126	b/i/b/a/c/g/e:c	(I)V
        //   353: goto -307 -> 46
        //   356: iload_3
        //   357: istore 7
        //   359: iload_3
        //   360: bipush 32
        //   362: iand
        //   363: bipush 32
        //   365: if_icmpeq +29 -> 394
        //   368: iload_3
        //   369: istore 4
        //   371: iload_3
        //   372: istore 5
        //   374: iload_3
        //   375: istore 6
        //   377: aload_0
        //   378: new 108	java/util/ArrayList
        //   381: dup
        //   382: invokespecial 109	java/util/ArrayList:<init>	()V
        //   385: putfield 111	b/i/b/a/c/e/b/b$g$b:f	Ljava/util/List;
        //   388: iload_3
        //   389: bipush 32
        //   391: ior
        //   392: istore 7
        //   394: iload 7
        //   396: istore 4
        //   398: iload 7
        //   400: istore 5
        //   402: iload 7
        //   404: istore 6
        //   406: aload_0
        //   407: getfield 111	b/i/b/a/c/e/b/b$g$b:f	Ljava/util/List;
        //   410: astore 11
        //   412: iload 7
        //   414: istore 4
        //   416: iload 7
        //   418: istore 5
        //   420: iload 7
        //   422: istore 6
        //   424: aload_1
        //   425: invokevirtual 101	b/i/b/a/c/g/e:d	()I
        //   428: invokestatic 117	java/lang/Integer:valueOf	(I)Ljava/lang/Integer;
        //   431: astore 12
        //   433: iload 7
        //   435: istore_3
        //   436: iload_3
        //   437: istore 4
        //   439: iload_3
        //   440: istore 5
        //   442: iload_3
        //   443: istore 6
        //   445: aload 11
        //   447: aload 12
        //   449: invokeinterface 123 2 0
        //   454: pop
        //   455: goto -409 -> 46
        //   458: iload_3
        //   459: istore 4
        //   461: iload_3
        //   462: istore 5
        //   464: iload_3
        //   465: istore 6
        //   467: aload_1
        //   468: aload_1
        //   469: invokevirtual 101	b/i/b/a/c/g/e:d	()I
        //   472: invokevirtual 104	b/i/b/a/c/g/e:b	(I)I
        //   475: istore 10
        //   477: iload_3
        //   478: istore 7
        //   480: iload_3
        //   481: bipush 16
        //   483: iand
        //   484: bipush 16
        //   486: if_icmpeq +48 -> 534
        //   489: iload_3
        //   490: istore 7
        //   492: iload_3
        //   493: istore 4
        //   495: iload_3
        //   496: istore 5
        //   498: iload_3
        //   499: istore 6
        //   501: aload_1
        //   502: invokevirtual 106	b/i/b/a/c/g/e:h	()I
        //   505: ifle +29 -> 534
        //   508: iload_3
        //   509: istore 4
        //   511: iload_3
        //   512: istore 5
        //   514: iload_3
        //   515: istore 6
        //   517: aload_0
        //   518: new 108	java/util/ArrayList
        //   521: dup
        //   522: invokespecial 109	java/util/ArrayList:<init>	()V
        //   525: putfield 128	b/i/b/a/c/e/b/b$g$b:e	Ljava/util/List;
        //   528: iload_3
        //   529: bipush 16
        //   531: ior
        //   532: istore 7
        //   534: iload 7
        //   536: istore_3
        //   537: iload 10
        //   539: istore 9
        //   541: iload 7
        //   543: istore 4
        //   545: iload 7
        //   547: istore 5
        //   549: iload 7
        //   551: istore 6
        //   553: aload_1
        //   554: invokevirtual 106	b/i/b/a/c/g/e:h	()I
        //   557: ifle -219 -> 338
        //   560: iload 7
        //   562: istore 4
        //   564: iload 7
        //   566: istore 5
        //   568: iload 7
        //   570: istore 6
        //   572: aload_0
        //   573: getfield 128	b/i/b/a/c/e/b/b$g$b:e	Ljava/util/List;
        //   576: aload_1
        //   577: invokevirtual 101	b/i/b/a/c/g/e:d	()I
        //   580: invokestatic 117	java/lang/Integer:valueOf	(I)Ljava/lang/Integer;
        //   583: invokeinterface 123 2 0
        //   588: pop
        //   589: goto -55 -> 534
        //   592: iload_3
        //   593: istore 7
        //   595: iload_3
        //   596: bipush 16
        //   598: iand
        //   599: bipush 16
        //   601: if_icmpeq +29 -> 630
        //   604: iload_3
        //   605: istore 4
        //   607: iload_3
        //   608: istore 5
        //   610: iload_3
        //   611: istore 6
        //   613: aload_0
        //   614: new 108	java/util/ArrayList
        //   617: dup
        //   618: invokespecial 109	java/util/ArrayList:<init>	()V
        //   621: putfield 128	b/i/b/a/c/e/b/b$g$b:e	Ljava/util/List;
        //   624: iload_3
        //   625: bipush 16
        //   627: ior
        //   628: istore 7
        //   630: iload 7
        //   632: istore 4
        //   634: iload 7
        //   636: istore 5
        //   638: iload 7
        //   640: istore 6
        //   642: aload_0
        //   643: getfield 128	b/i/b/a/c/e/b/b$g$b:e	Ljava/util/List;
        //   646: astore 11
        //   648: iload 7
        //   650: istore 4
        //   652: iload 7
        //   654: istore 5
        //   656: iload 7
        //   658: istore 6
        //   660: aload_1
        //   661: invokevirtual 101	b/i/b/a/c/g/e:d	()I
        //   664: invokestatic 117	java/lang/Integer:valueOf	(I)Ljava/lang/Integer;
        //   667: astore 12
        //   669: iload 7
        //   671: istore_3
        //   672: goto -236 -> 436
        //   675: iload_3
        //   676: istore 4
        //   678: iload_3
        //   679: istore 5
        //   681: iload_3
        //   682: istore 6
        //   684: aload_1
        //   685: invokevirtual 101	b/i/b/a/c/g/e:d	()I
        //   688: istore 9
        //   690: iload_3
        //   691: istore 4
        //   693: iload_3
        //   694: istore 5
        //   696: iload_3
        //   697: istore 6
        //   699: iload 9
        //   701: invokestatic 131	b/i/b/a/c/e/b/b$g$b$b:a	(I)Lb/i/b/a/c/e/b/b$g$b$b;
        //   704: astore 11
        //   706: aload 11
        //   708: ifnonnull +38 -> 746
        //   711: iload_3
        //   712: istore 4
        //   714: iload_3
        //   715: istore 5
        //   717: iload_3
        //   718: istore 6
        //   720: aload 14
        //   722: iload 7
        //   724: invokevirtual 133	b/i/b/a/c/g/f:e	(I)V
        //   727: iload_3
        //   728: istore 4
        //   730: iload_3
        //   731: istore 5
        //   733: iload_3
        //   734: istore 6
        //   736: aload 14
        //   738: iload 9
        //   740: invokevirtual 133	b/i/b/a/c/g/f:e	(I)V
        //   743: goto -697 -> 46
        //   746: iload_3
        //   747: istore 4
        //   749: iload_3
        //   750: istore 5
        //   752: iload_3
        //   753: istore 6
        //   755: aload_0
        //   756: aload_0
        //   757: getfield 97	b/i/b/a/c/e/b/b$g$b:i	I
        //   760: bipush 8
        //   762: ior
        //   763: putfield 97	b/i/b/a/c/e/b/b$g$b:i	I
        //   766: iload_3
        //   767: istore 4
        //   769: iload_3
        //   770: istore 5
        //   772: iload_3
        //   773: istore 6
        //   775: aload_0
        //   776: aload 11
        //   778: putfield 135	b/i/b/a/c/e/b/b$g$b:d	Lb/i/b/a/c/e/b/b$g$b$b;
        //   781: goto -735 -> 46
        //   784: iload_3
        //   785: istore 4
        //   787: iload_3
        //   788: istore 5
        //   790: iload_3
        //   791: istore 6
        //   793: aload_0
        //   794: aload_0
        //   795: getfield 97	b/i/b/a/c/e/b/b$g$b:i	I
        //   798: iconst_2
        //   799: ior
        //   800: putfield 97	b/i/b/a/c/e/b/b$g$b:i	I
        //   803: iload_3
        //   804: istore 4
        //   806: iload_3
        //   807: istore 5
        //   809: iload_3
        //   810: istore 6
        //   812: aload_0
        //   813: aload_1
        //   814: invokevirtual 101	b/i/b/a/c/g/e:d	()I
        //   817: putfield 137	b/i/b/a/c/e/b/b$g$b:c	I
        //   820: goto -774 -> 46
        //   823: iload_3
        //   824: istore 4
        //   826: iload_3
        //   827: istore 5
        //   829: iload_3
        //   830: istore 6
        //   832: aload_0
        //   833: aload_0
        //   834: getfield 97	b/i/b/a/c/e/b/b$g$b:i	I
        //   837: iconst_1
        //   838: ior
        //   839: putfield 97	b/i/b/a/c/e/b/b$g$b:i	I
        //   842: iload_3
        //   843: istore 4
        //   845: iload_3
        //   846: istore 5
        //   848: iload_3
        //   849: istore 6
        //   851: aload_0
        //   852: aload_1
        //   853: invokevirtual 101	b/i/b/a/c/g/e:d	()I
        //   856: putfield 139	b/i/b/a/c/e/b/b$g$b:b	I
        //   859: goto -813 -> 46
        //   862: iconst_1
        //   863: istore 8
        //   865: goto -819 -> 46
        //   868: astore_1
        //   869: goto +51 -> 920
        //   872: astore_1
        //   873: iload 5
        //   875: istore 4
        //   877: new 74	b/i/b/a/c/g/k
        //   880: dup
        //   881: aload_1
        //   882: invokevirtual 143	java/io/IOException:getMessage	()Ljava/lang/String;
        //   885: invokespecial 146	b/i/b/a/c/g/k:<init>	(Ljava/lang/String;)V
        //   888: astore_1
        //   889: iload 5
        //   891: istore 4
        //   893: aload_1
        //   894: aload_0
        //   895: putfield 149	b/i/b/a/c/g/k:a	Lb/i/b/a/c/g/q;
        //   898: iload 5
        //   900: istore 4
        //   902: aload_1
        //   903: athrow
        //   904: astore_1
        //   905: iload 6
        //   907: istore 4
        //   909: aload_1
        //   910: aload_0
        //   911: putfield 149	b/i/b/a/c/g/k:a	Lb/i/b/a/c/g/q;
        //   914: iload 6
        //   916: istore 4
        //   918: aload_1
        //   919: athrow
        //   920: iload 4
        //   922: bipush 16
        //   924: iand
        //   925: bipush 16
        //   927: if_icmpne +14 -> 941
        //   930: aload_0
        //   931: aload_0
        //   932: getfield 128	b/i/b/a/c/e/b/b$g$b:e	Ljava/util/List;
        //   935: invokestatic 155	java/util/Collections:unmodifiableList	(Ljava/util/List;)Ljava/util/List;
        //   938: putfield 128	b/i/b/a/c/e/b/b$g$b:e	Ljava/util/List;
        //   941: iload 4
        //   943: bipush 32
        //   945: iand
        //   946: bipush 32
        //   948: if_icmpne +14 -> 962
        //   951: aload_0
        //   952: aload_0
        //   953: getfield 111	b/i/b/a/c/e/b/b$g$b:f	Ljava/util/List;
        //   956: invokestatic 155	java/util/Collections:unmodifiableList	(Ljava/util/List;)Ljava/util/List;
        //   959: putfield 111	b/i/b/a/c/e/b/b$g$b:f	Ljava/util/List;
        //   962: aload 14
        //   964: invokevirtual 157	b/i/b/a/c/g/f:a	()V
        //   967: aload_0
        //   968: aload 13
        //   970: invokevirtual 161	b/i/b/a/c/g/d$b:a	()Lb/i/b/a/c/g/d;
        //   973: putfield 71	b/i/b/a/c/e/b/b$g$b:h	Lb/i/b/a/c/g/d;
        //   976: goto +15 -> 991
        //   979: astore_1
        //   980: aload_0
        //   981: aload 13
        //   983: invokevirtual 161	b/i/b/a/c/g/d$b:a	()Lb/i/b/a/c/g/d;
        //   986: putfield 71	b/i/b/a/c/e/b/b$g$b:h	Lb/i/b/a/c/g/d;
        //   989: aload_1
        //   990: athrow
        //   991: aload_0
        //   992: invokevirtual 164	b/i/b/a/c/e/b/b$g$b:w	()V
        //   995: aload_1
        //   996: athrow
        //   997: iload_3
        //   998: bipush 16
        //   1000: iand
        //   1001: bipush 16
        //   1003: if_icmpne +14 -> 1017
        //   1006: aload_0
        //   1007: aload_0
        //   1008: getfield 128	b/i/b/a/c/e/b/b$g$b:e	Ljava/util/List;
        //   1011: invokestatic 155	java/util/Collections:unmodifiableList	(Ljava/util/List;)Ljava/util/List;
        //   1014: putfield 128	b/i/b/a/c/e/b/b$g$b:e	Ljava/util/List;
        //   1017: iload_3
        //   1018: bipush 32
        //   1020: iand
        //   1021: bipush 32
        //   1023: if_icmpne +14 -> 1037
        //   1026: aload_0
        //   1027: aload_0
        //   1028: getfield 111	b/i/b/a/c/e/b/b$g$b:f	Ljava/util/List;
        //   1031: invokestatic 155	java/util/Collections:unmodifiableList	(Ljava/util/List;)Ljava/util/List;
        //   1034: putfield 111	b/i/b/a/c/e/b/b$g$b:f	Ljava/util/List;
        //   1037: aload 14
        //   1039: invokevirtual 157	b/i/b/a/c/g/f:a	()V
        //   1042: aload_0
        //   1043: aload 13
        //   1045: invokevirtual 161	b/i/b/a/c/g/d$b:a	()Lb/i/b/a/c/g/d;
        //   1048: putfield 71	b/i/b/a/c/e/b/b$g$b:h	Lb/i/b/a/c/g/d;
        //   1051: goto +15 -> 1066
        //   1054: astore_1
        //   1055: aload_0
        //   1056: aload 13
        //   1058: invokevirtual 161	b/i/b/a/c/g/d$b:a	()Lb/i/b/a/c/g/d;
        //   1061: putfield 71	b/i/b/a/c/e/b/b$g$b:h	Lb/i/b/a/c/g/d;
        //   1064: aload_1
        //   1065: athrow
        //   1066: aload_0
        //   1067: invokevirtual 164	b/i/b/a/c/e/b/b$g$b:w	()V
        //   1070: return
        //   1071: astore_2
        //   1072: goto -105 -> 967
        //   1075: astore_1
        //   1076: goto -34 -> 1042
        // Local variable table:
        //   start	length	slot	name	signature
        //   0	1079	0	this	b
        //   0	1079	1	parame	b.i.b.a.c.g.e
        //   0	1079	2	paramg	g
        //   45	976	3	i1	int
        //   52	894	4	i2	int
        //   55	844	5	i3	int
        //   58	857	6	i4	int
        //   64	659	7	i5	int
        //   42	822	8	i6	int
        //   285	454	9	i7	int
        //   221	317	10	i8	int
        //   165	612	11	localObject	Object
        //   431	237	12	localInteger	Integer
        //   31	1026	13	localb	b.i.b.a.c.g.d.b
        //   39	999	14	localf	f
        // Exception table:
        //   from	to	target	type
        //   60	66	868	finally
        //   136	149	868	finally
        //   161	167	868	finally
        //   176	186	868	finally
        //   195	201	868	finally
        //   213	223	868	finally
        //   247	254	868	finally
        //   263	274	868	finally
        //   299	306	868	finally
        //   318	335	868	finally
        //   347	353	868	finally
        //   377	388	868	finally
        //   406	412	868	finally
        //   424	433	868	finally
        //   445	455	868	finally
        //   467	477	868	finally
        //   501	508	868	finally
        //   517	528	868	finally
        //   553	560	868	finally
        //   572	589	868	finally
        //   613	624	868	finally
        //   642	648	868	finally
        //   660	669	868	finally
        //   684	690	868	finally
        //   699	706	868	finally
        //   720	727	868	finally
        //   736	743	868	finally
        //   755	766	868	finally
        //   775	781	868	finally
        //   793	803	868	finally
        //   812	820	868	finally
        //   832	842	868	finally
        //   851	859	868	finally
        //   877	889	868	finally
        //   893	898	868	finally
        //   902	904	868	finally
        //   909	914	868	finally
        //   918	920	868	finally
        //   60	66	872	java/io/IOException
        //   136	149	872	java/io/IOException
        //   161	167	872	java/io/IOException
        //   176	186	872	java/io/IOException
        //   195	201	872	java/io/IOException
        //   213	223	872	java/io/IOException
        //   247	254	872	java/io/IOException
        //   263	274	872	java/io/IOException
        //   299	306	872	java/io/IOException
        //   318	335	872	java/io/IOException
        //   347	353	872	java/io/IOException
        //   377	388	872	java/io/IOException
        //   406	412	872	java/io/IOException
        //   424	433	872	java/io/IOException
        //   445	455	872	java/io/IOException
        //   467	477	872	java/io/IOException
        //   501	508	872	java/io/IOException
        //   517	528	872	java/io/IOException
        //   553	560	872	java/io/IOException
        //   572	589	872	java/io/IOException
        //   613	624	872	java/io/IOException
        //   642	648	872	java/io/IOException
        //   660	669	872	java/io/IOException
        //   684	690	872	java/io/IOException
        //   699	706	872	java/io/IOException
        //   720	727	872	java/io/IOException
        //   736	743	872	java/io/IOException
        //   755	766	872	java/io/IOException
        //   775	781	872	java/io/IOException
        //   793	803	872	java/io/IOException
        //   812	820	872	java/io/IOException
        //   832	842	872	java/io/IOException
        //   851	859	872	java/io/IOException
        //   60	66	904	b/i/b/a/c/g/k
        //   136	149	904	b/i/b/a/c/g/k
        //   161	167	904	b/i/b/a/c/g/k
        //   176	186	904	b/i/b/a/c/g/k
        //   195	201	904	b/i/b/a/c/g/k
        //   213	223	904	b/i/b/a/c/g/k
        //   247	254	904	b/i/b/a/c/g/k
        //   263	274	904	b/i/b/a/c/g/k
        //   299	306	904	b/i/b/a/c/g/k
        //   318	335	904	b/i/b/a/c/g/k
        //   347	353	904	b/i/b/a/c/g/k
        //   377	388	904	b/i/b/a/c/g/k
        //   406	412	904	b/i/b/a/c/g/k
        //   424	433	904	b/i/b/a/c/g/k
        //   445	455	904	b/i/b/a/c/g/k
        //   467	477	904	b/i/b/a/c/g/k
        //   501	508	904	b/i/b/a/c/g/k
        //   517	528	904	b/i/b/a/c/g/k
        //   553	560	904	b/i/b/a/c/g/k
        //   572	589	904	b/i/b/a/c/g/k
        //   613	624	904	b/i/b/a/c/g/k
        //   642	648	904	b/i/b/a/c/g/k
        //   660	669	904	b/i/b/a/c/g/k
        //   684	690	904	b/i/b/a/c/g/k
        //   699	706	904	b/i/b/a/c/g/k
        //   720	727	904	b/i/b/a/c/g/k
        //   736	743	904	b/i/b/a/c/g/k
        //   755	766	904	b/i/b/a/c/g/k
        //   775	781	904	b/i/b/a/c/g/k
        //   793	803	904	b/i/b/a/c/g/k
        //   812	820	904	b/i/b/a/c/g/k
        //   832	842	904	b/i/b/a/c/g/k
        //   851	859	904	b/i/b/a/c/g/k
        //   962	967	979	finally
        //   1037	1042	1054	finally
        //   962	967	1071	java/io/IOException
        //   1037	1042	1075	java/io/IOException
      }
      
      private b(i.a parama)
      {
        super();
        this.h = parama.a;
      }
      
      public static b a()
      {
        return g;
      }
      
      private d o()
      {
        Object localObject = this.j;
        if ((localObject instanceof String))
        {
          localObject = d.a((String)localObject);
          this.j = localObject;
          return (d)localObject;
        }
        return (d)localObject;
      }
      
      private void p()
      {
        this.b = 1;
        this.c = 0;
        this.j = "";
        this.d = b.a;
        this.e = Collections.emptyList();
        this.f = Collections.emptyList();
      }
      
      public final void a(f paramf)
        throws IOException
      {
        f();
        if ((this.i & 0x1) == 1) {
          paramf.a(1, this.b);
        }
        if ((this.i & 0x2) == 2) {
          paramf.a(2, this.c);
        }
        if ((this.i & 0x8) == 8) {
          paramf.b(3, this.d.d);
        }
        if (this.e.size() > 0)
        {
          paramf.e(34);
          paramf.e(this.k);
        }
        int i2 = 0;
        int i1 = 0;
        while (i1 < this.e.size())
        {
          paramf.a(((Integer)this.e.get(i1)).intValue());
          i1 += 1;
        }
        i1 = i2;
        if (this.f.size() > 0)
        {
          paramf.e(42);
          paramf.e(this.l);
          i1 = i2;
        }
        while (i1 < this.f.size())
        {
          paramf.a(((Integer)this.f.get(i1)).intValue());
          i1 += 1;
        }
        if ((this.i & 0x4) == 4) {
          paramf.a(6, o());
        }
        paramf.c(this.h);
      }
      
      public final s<b> b()
      {
        return a;
      }
      
      public final boolean c()
      {
        return (this.i & 0x1) == 1;
      }
      
      public final boolean d()
      {
        return (this.i & 0x2) == 2;
      }
      
      public final boolean e()
      {
        int i1 = this.m;
        if (i1 == 1) {
          return true;
        }
        if (i1 == 0) {
          return false;
        }
        this.m = 1;
        return true;
      }
      
      public final int f()
      {
        int i1 = this.n;
        if (i1 != -1) {
          return i1;
        }
        i1 = this.i;
        int i4 = 0;
        if ((i1 & 0x1) == 1) {
          i2 = f.c(1, this.b) + 0;
        } else {
          i2 = 0;
        }
        i1 = i2;
        if ((this.i & 0x2) == 2) {
          i1 = i2 + f.c(2, this.c);
        }
        int i2 = i1;
        if ((this.i & 0x8) == 8) {
          i2 = i1 + f.d(3, this.d.d);
        }
        i1 = 0;
        int i3 = 0;
        while (i1 < this.e.size())
        {
          i3 += f.c(((Integer)this.e.get(i1)).intValue());
          i1 += 1;
        }
        i2 += i3;
        i1 = i2;
        if (!this.e.isEmpty()) {
          i1 = i2 + 1 + f.c(i3);
        }
        this.k = i3;
        i2 = 0;
        i3 = i4;
        while (i3 < this.f.size())
        {
          i2 += f.c(((Integer)this.f.get(i3)).intValue());
          i3 += 1;
        }
        i3 = i1 + i2;
        i1 = i3;
        if (!this.f.isEmpty()) {
          i1 = i3 + 1 + f.c(i2);
        }
        this.l = i2;
        i2 = i1;
        if ((this.i & 0x4) == 4) {
          i2 = i1 + f.b(6, o());
        }
        i1 = i2 + this.h.a();
        this.n = i1;
        return i1;
      }
      
      public final boolean g()
      {
        return (this.i & 0x4) == 4;
      }
      
      public final String k()
      {
        Object localObject = this.j;
        if ((localObject instanceof String)) {
          return (String)localObject;
        }
        localObject = (d)localObject;
        String str = ((d)localObject).e();
        if (((d)localObject).f()) {
          this.j = str;
        }
        return str;
      }
      
      public final boolean l()
      {
        return (this.i & 0x8) == 8;
      }
      
      public final int m()
      {
        return this.e.size();
      }
      
      public final int n()
      {
        return this.f.size();
      }
      
      public static final class a
        extends i.a<b.g.b, a>
        implements b.g.c
      {
        private int b;
        private int c = 1;
        private int d;
        private Object e = "";
        private b.g.b.b f = b.g.b.b.a;
        private List<Integer> g = Collections.emptyList();
        private List<Integer> h = Collections.emptyList();
        
        private a a(int paramInt)
        {
          this.b |= 0x1;
          this.c = paramInt;
          return this;
        }
        
        private a a(b.g.b.b paramb)
        {
          if (paramb != null)
          {
            this.b |= 0x8;
            this.f = paramb;
            return this;
          }
          throw new NullPointerException();
        }
        
        private a b(int paramInt)
        {
          this.b |= 0x2;
          this.d = paramInt;
          return this;
        }
        
        /* Error */
        private a c(b.i.b.a.c.g.e parame, g paramg)
          throws IOException
        {
          // Byte code:
          //   0: aconst_null
          //   1: astore_3
          //   2: getstatic 70	b/i/b/a/c/e/b/b$g$b:a	Lb/i/b/a/c/g/s;
          //   5: aload_1
          //   6: aload_2
          //   7: invokeinterface 75 3 0
          //   12: checkcast 14	b/i/b/a/c/e/b/b$g$b
          //   15: astore_1
          //   16: aload_0
          //   17: aload_1
          //   18: invokevirtual 78	b/i/b/a/c/e/b/b$g$b$a:a	(Lb/i/b/a/c/e/b/b$g$b;)Lb/i/b/a/c/e/b/b$g$b$a;
          //   21: pop
          //   22: aload_0
          //   23: areturn
          //   24: astore_2
          //   25: aload_3
          //   26: astore_1
          //   27: goto +15 -> 42
          //   30: astore_2
          //   31: aload_2
          //   32: getfield 81	b/i/b/a/c/g/k:a	Lb/i/b/a/c/g/q;
          //   35: checkcast 14	b/i/b/a/c/e/b/b$g$b
          //   38: astore_1
          //   39: aload_2
          //   40: athrow
          //   41: astore_2
          //   42: aload_1
          //   43: ifnull +9 -> 52
          //   46: aload_0
          //   47: aload_1
          //   48: invokevirtual 78	b/i/b/a/c/e/b/b$g$b$a:a	(Lb/i/b/a/c/e/b/b$g$b;)Lb/i/b/a/c/e/b/b$g$b$a;
          //   51: pop
          //   52: aload_2
          //   53: athrow
          // Local variable table:
          //   start	length	slot	name	signature
          //   0	54	0	this	a
          //   0	54	1	parame	b.i.b.a.c.g.e
          //   0	54	2	paramg	g
          //   1	25	3	localObject	Object
          // Exception table:
          //   from	to	target	type
          //   2	16	24	finally
          //   31	39	24	finally
          //   2	16	30	b/i/b/a/c/g/k
          //   39	41	41	finally
        }
        
        private a g()
        {
          return new a().a(h());
        }
        
        private b.g.b h()
        {
          int j = 0;
          b.g.b localb = new b.g.b(this, (byte)0);
          int k = this.b;
          if ((k & 0x1) == 1) {
            j = 1;
          }
          b.g.b.a(localb, this.c);
          int i = j;
          if ((k & 0x2) == 2) {
            i = j | 0x2;
          }
          b.g.b.b(localb, this.d);
          j = i;
          if ((k & 0x4) == 4) {
            j = i | 0x4;
          }
          b.g.b.a(localb, this.e);
          i = j;
          if ((k & 0x8) == 8) {
            i = j | 0x8;
          }
          b.g.b.a(localb, this.f);
          if ((this.b & 0x10) == 16)
          {
            this.g = Collections.unmodifiableList(this.g);
            this.b &= 0xFFFFFFEF;
          }
          b.g.b.a(localb, this.g);
          if ((this.b & 0x20) == 32)
          {
            this.h = Collections.unmodifiableList(this.h);
            this.b &= 0xFFFFFFDF;
          }
          b.g.b.b(localb, this.h);
          b.g.b.c(localb, i);
          return localb;
        }
        
        private void i()
        {
          if ((this.b & 0x10) != 16)
          {
            this.g = new ArrayList(this.g);
            this.b |= 0x10;
          }
        }
        
        private void k()
        {
          if ((this.b & 0x20) != 32)
          {
            this.h = new ArrayList(this.h);
            this.b |= 0x20;
          }
        }
        
        public final a a(b.g.b paramb)
        {
          if (paramb == b.g.b.a()) {
            return this;
          }
          if (paramb.c()) {
            a(paramb.b);
          }
          if (paramb.d()) {
            b(paramb.c);
          }
          if (paramb.g())
          {
            this.b |= 0x4;
            this.e = b.g.b.a(paramb);
          }
          if (paramb.l()) {
            a(paramb.d);
          }
          if (!b.g.b.b(paramb).isEmpty()) {
            if (this.g.isEmpty())
            {
              this.g = b.g.b.b(paramb);
              this.b &= 0xFFFFFFEF;
            }
            else
            {
              i();
              this.g.addAll(b.g.b.b(paramb));
            }
          }
          if (!b.g.b.c(paramb).isEmpty()) {
            if (this.h.isEmpty())
            {
              this.h = b.g.b.c(paramb);
              this.b &= 0xFFFFFFDF;
            }
            else
            {
              k();
              this.h.addAll(b.g.b.c(paramb));
            }
          }
          this.a = this.a.a(b.g.b.d(paramb));
          return this;
        }
        
        public final boolean e()
        {
          return true;
        }
      }
      
      public static enum b
        implements j.a
      {
        private static j.b<b> e = new j.b() {};
        final int d;
        
        private b(int paramInt1, int paramInt2)
        {
          this.d = paramInt1;
        }
        
        public static b a(int paramInt)
        {
          switch (paramInt)
          {
          default: 
            return null;
          case 2: 
            return c;
          case 1: 
            return b;
          }
          return a;
        }
        
        public final int a()
        {
          return this.d;
        }
      }
    }
    
    public static abstract interface c
      extends r
    {}
  }
  
  public static abstract interface h
    extends r
  {}
}


/* Location:              /home/kmille/projects/android-pwning/apks/aldi/ALDI TALK_v6.2.1_apkpure.com-dex2jar.jar!/b/i/b/a/c/e/b/b.class
 * Java compiler version: 6 (50.0)
 * JD-Core Version:       0.7.1
 */